Workbook

Sheet Bank_Rates
A1: Issuer | B1: Timestamp | C1: Interest Rate | D1: Duration (Days)
A2: MBB | B2: 46244 | C2: 0.018 | D2: 1
A3: MBB | B3: 46244 | C3: 0.04 | D3: 21
A4: MBB | B4: 46244 | C4: 0.065 | D4: 30
A5: MBB | B5: 46244 | C5: 0.067 | D5: 60
A6: MBB | B6: 46244 | C6: 0.07 | D6: 90
A7: MBB | B7: 46244 | C7: 0.07 | D7: 120
A8: MBB | B8: 46244 | C8: 0.07 | D8: 150
A9: MBB | B9: 46244 | C9: 0.071 | D9: 180
A10: MBB | B10: 46244 | C10: 0.071 | D10: 210
A11: MBB | B11: 46244 | C11: 0.071 | D11: 240
A12: MBB | B12: 46244 | C12: 0.071 | D12: 270
A13: MBB | B13: 46244 | C13: 0.02 | D13: 7
A14: MBB | B14: 46244 | C14: 0.03 | D14: 14

Sheet Raw_Observations
A1: Listing ID | B1: CD ID | C1: Timestamp | D1: Price ($) | E1: Value at Maturity ($) | F1: Maturity Date | G1: Remaining Duration (Days) | H1: Issuer | I1: Effective YTM | J1: Corresponding Rate | K1: Entry Spread
A2: =IF(B2<>"","L-"&TEXT(ROW()-1,"0000"),"") -> L-0001 | B2: TP03077 | C2: 46253 | D2: 4653638 | E2: 4671001 | F2: 46274 | G2: =IF(OR(C2="",F2=""),"",F2-C2) -> 21 | H2: MBB | I2: =IF(OR(D2="",E2="",G2="",G2=0),"",(E2/D2)^(365/G2)-1) -> 0.066869531 | J2: =IFERROR(SUMIFS(Bank_Rates!$C$2:$C$100,Bank_Rates!$A$2:$A$100,H2,Bank_Rates!$B$2:$B$100,LOOKUP(2,1/((Bank_Rates!$A$2:$A$100=H2)*(Bank_Rates!$B$2:$B$100<=C2)),Bank_Rates!$B$2:$B$100),Bank_Rates!$D$2:$D$100,_xlfn.AGGREGATE(14,6,Bank_Rates!$D$2:$D$100/((Bank_Rates!$A$2:$A$100=H2)*(Bank_Rates!$B$2:$B$100=LOOKUP(2,1/((Bank_Rates!$A$2:$A$100=H2)*(Bank_Rates!$B$2:$B$100<=C2)),Bank_Rates!$B$2:$B$100))*(Bank_Rates!$D$2:$D$100<=G2)),1)),"No Match") -> 0.04 | K2: =IF(OR(I2="",J2="",J2="No Match"),"",I2-J2) -> 0.026869531
A3: =IF(B3<>"","L-"&TEXT(ROW()-1,"0000"),"") -> L-0002 | B3: TP03085 | C3: 46253 | D3: 3508365 | E3: 3520202 | F3: 46272 | G3: =IF(OR(C3="",F3=""),"",F3-C3) -> 19 | H3: MBB | I3: =IF(OR(D3="",E3="",G3="",G3=0),"",(E3/D3)^(365/G3)-1) -> 0.066845322 | J3: =IFERROR(SUMIFS(Bank_Rates!$C$2:$C$100,Bank_Rates!$A$2:$A$100,H3,Bank_Rates!$B$2:$B$100,LOOKUP(2,1/((Bank_Rates!$A$2:$A$100=H3)*(Bank_Rates!$B$2:$B$100<=C3)),Bank_Rates!$B$2:$B$100),Bank_Rates!$D$2:$D$100,_xlfn.AGGREGATE(14,6,Bank_Rates!$D$2:$D$100/((Bank_Rates!$A$2:$A$100=H3)*(Bank_Rates!$B$2:$B$100=LOOKUP(2,1/((Bank_Rates!$A$2:$A$100=H3)*(Bank_Rates!$B$2:$B$100<=C3)),Bank_Rates!$B$2:$B$100))*(Bank_Rates!$D$2:$D$100<=G3)),1)),"No Match") -> 0.03 | K3: =IF(OR(I3="",J3="",J3="No Match"),"",I3-J3) -> 0.036845322
A4: =IF(B4<>"","L-"&TEXT(ROW()-1,"0000"),"") -> L-0003 | B4: TP03093 | C4: 46253 | D4: 4610986 | E4: 4626551 | F4: 46272 | G4: =IF(OR(C4="",F4=""),"",F4-C4) -> 19 | H4: MBB | I4: =IF(OR(D4="",E4="",G4="",G4=0),"",(E4/D4)^(365/G4)-1) -> 0.066879994 | J4: =IFERROR(SUMIFS(Bank_Rates!$C$2:$C$100,Bank_Rates!$A$2:$A$100,H4,Bank_Rates!$B$2:$B$100,LOOKUP(2,1/((Bank_Rates!$A$2:$A$100=H4)*(Bank_Rates!$B$2:$B$100<=C4)),Bank_Rates!$B$2:$B$100),Bank_Rates!$D$2:$D$100,_xlfn.AGGREGATE(14,6,Bank_Rates!$D$2:$D$100/((Bank_Rates!$A$2:$A$100=H4)*(Bank_Rates!$B$2:$B$100=LOOKUP(2,1/((Bank_Rates!$A$2:$A$100=H4)*(Bank_Rates!$B$2:$B$100<=C4)),Bank_Rates!$B$2:$B$100))*(Bank_Rates!$D$2:$D$100<=G4)),1)),"No Match") -> 0.03 | K4: =IF(OR(I4="",J4="",J4="No Match"),"",I4-J4) -> 0.036879994
A5: =IF(B5<>"","L-"&TEXT(ROW()-1,"0000"),"") -> L-0004 | B5: TP03104 | C5: 46253 | D5: 3508456 | E5: 3520202 | F5: 46272 | G5: =IF(OR(C5="",F5=""),"",F5-C5) -> 19 | H5: MBB | I5: =IF(OR(D5="",E5="",G5="",G5=0),"",(E5/D5)^(365/G5)-1) -> 0.06631387 | J5: =IFERROR(SUMIFS(Bank_Rates!$C$2:$C$100,Bank_Rates!$A$2:$A$100,H5,Bank_Rates!$B$2:$B$100,LOOKUP(2,1/((Bank_Rates!$A$2:$A$100=H5)*(Bank_Rates!$B$2:$B$100<=C5)),Bank_Rates!$B$2:$B$100),Bank_Rates!$D$2:$D$100,_xlfn.AGGREGATE(14,6,Bank_Rates!$D$2:$D$100/((Bank_Rates!$A$2:$A$100=H5)*(Bank_Rates!$B$2:$B$100=LOOKUP(2,1/((Bank_Rates!$A$2:$A$100=H5)*(Bank_Rates!$B$2:$B$100<=C5)),Bank_Rates!$B$2:$B$100))*(Bank_Rates!$D$2:$D$100<=G5)),1)),"No Match") -> 0.03 | K5: =IF(OR(I5="",J5="",J5="No Match"),"",I5-J5) -> 0.03631387
A6: =IF(B6<>"","L-"&TEXT(ROW()-1,"0000"),"") -> L-0005 | B6: TP00964 | C6: 46245 | D6: 6671860 | E6: 6749674 | F6: 46305 | G6: =IF(OR(C6="",F6=""),"",F6-C6) -> 60 | H6: MBB | I6: =IF(OR(D6="",E6="",G6="",G6=0),"",(E6/D6)^(365/G6)-1) -> 0.0730869 | J6: =IFERROR(SUMIFS(Bank_Rates!$C$2:$C$100,Bank_Rates!$A$2:$A$100,H6,Bank_Rates!$B$2:$B$100,LOOKUP(2,1/((Bank_Rates!$A$2:$A$100=H6)*(Bank_Rates!$B$2:$B$100<=C6)),Bank_Rates!$B$2:$B$100),Bank_Rates!$D$2:$D$100,_xlfn.AGGREGATE(14,6,Bank_Rates!$D$2:$D$100/((Bank_Rates!$A$2:$A$100=H6)*(Bank_Rates!$B$2:$B$100=LOOKUP(2,1/((Bank_Rates!$A$2:$A$100=H6)*(Bank_Rates!$B$2:$B$100<=C6)),Bank_Rates!$B$2:$B$100))*(Bank_Rates!$D$2:$D$100<=G6)),1)),"No Match") -> 0.067 | K6: =IF(OR(I6="",J6="",J6="No Match"),"",I6-J6) -> 0.0060869004
A7: =IF(B7<>"","L-"&TEXT(ROW()-1,"0000"),"") -> L-0006 | B7: TP03429 | C7: 46247 | D7: 20060000 | E7: 20826744 | F7: 46430 | G7: =IF(OR(C7="",F7=""),"",F7-C7) -> 183 | H7: MBB | I7: =IF(OR(D7="",E7="",G7="",G7=0),"",(E7/D7)^(365/G7)-1) -> 0.077685107 | J7: =IFERROR(SUMIFS(Bank_Rates!$C$2:$C$100,Bank_Rates!$A$2:$A$100,H7,Bank_Rates!$B$2:$B$100,LOOKUP(2,1/((Bank_Rates!$A$2:$A$100=H7)*(Bank_Rates!$B$2:$B$100<=C7)),Bank_Rates!$B$2:$B$100),Bank_Rates!$D$2:$D$100,_xlfn.AGGREGATE(14,6,Bank_Rates!$D$2:$D$100/((Bank_Rates!$A$2:$A$100=H7)*(Bank_Rates!$B$2:$B$100=LOOKUP(2,1/((Bank_Rates!$A$2:$A$100=H7)*(Bank_Rates!$B$2:$B$100<=C7)),Bank_Rates!$B$2:$B$100))*(Bank_Rates!$D$2:$D$100<=G7)),1)),"No Match") -> 0.071 | K7: =IF(OR(I7="",J7="",J7="No Match"),"",I7-J7) -> 0.0066851073
A8: =IF(B8<>"","L-"&TEXT(ROW()-1,"0000"),"") -> L-0007 | B8: TP00537 | C8: 46248 | D8: 29685213 | E8: 30297331 | F8: 46346 | G8: =IF(OR(C8="",F8=""),"",F8-C8) -> 98 | H8: MBB | I8: =IF(OR(D8="",E8="",G8="",G8=0),"",(E8/D8)^(365/G8)-1) -> 0.07898307 | J8: =IFERROR(SUMIFS(Bank_Rates!$C$2:$C$100,Bank_Rates!$A$2:$A$100,H8,Bank_Rates!$B$2:$B$100,LOOKUP(2,1/((Bank_Rates!$A$2:$A$100=H8)*(Bank_Rates!$B$2:$B$100<=C8)),Bank_Rates!$B$2:$B$100),Bank_Rates!$D$2:$D$100,_xlfn.AGGREGATE(14,6,Bank_Rates!$D$2:$D$100/((Bank_Rates!$A$2:$A$100=H8)*(Bank_Rates!$B$2:$B$100=LOOKUP(2,1/((Bank_Rates!$A$2:$A$100=H8)*(Bank_Rates!$B$2:$B$100<=C8)),Bank_Rates!$B$2:$B$100))*(Bank_Rates!$D$2:$D$100<=G8)),1)),"No Match") -> 0.07 | K8: =IF(OR(I8="",J8="",J8="No Match"),"",I8-J8) -> 0.0089830705
A9: =IF(B9<>"","L-"&TEXT(ROW()-1,"0000"),"") -> L-0008 | B9: TP01034 | C9: 46248 | D9: 30046000 | E9: 31206091 | F9: 46431 | G9: =IF(OR(C9="",F9=""),"",F9-C9) -> 183 | H9: MBB | I9: =IF(OR(D9="",E9="",G9="",G9=0),"",(E9/D9)^(365/G9)-1) -> 0.078488478 | J9: =IFERROR(SUMIFS(Bank_Rates!$C$2:$C$100,Bank_Rates!$A$2:$A$100,H9,Bank_Rates!$B$2:$B$100,LOOKUP(2,1/((Bank_Rates!$A$2:$A$100=H9)*(Bank_Rates!$B$2:$B$100<=C9)),Bank_Rates!$B$2:$B$100),Bank_Rates!$D$2:$D$100,_xlfn.AGGREGATE(14,6,Bank_Rates!$D$2:$D$100/((Bank_Rates!$A$2:$A$100=H9)*(Bank_Rates!$B$2:$B$100=LOOKUP(2,1/((Bank_Rates!$A$2:$A$100=H9)*(Bank_Rates!$B$2:$B$100<=C9)),Bank_Rates!$B$2:$B$100))*(Bank_Rates!$D$2:$D$100<=G9)),1)),"No Match") -> 0.071 | K9: =IF(OR(I9="",J9="",J9="No Match"),"",I9-J9) -> 0.0074884785
A10: =IF(B10<>"","L-"&TEXT(ROW()-1,"0000"),"") -> L-0009 | B10: TP00945 | C10: 46251 | D10: 20064000 | E10: 20110411 | F10: 46264 | G10: =IF(OR(C10="",F10=""),"",F10-C10) -> 13 | H10: MBB | I10: =IF(OR(D10="",E10="",G10="",G10=0),"",(E10/D10)^(365/G10)-1) -> 0.067021452 | J10: =IFERROR(SUMIFS(Bank_Rates!$C$2:$C$100,Bank_Rates!$A$2:$A$100,H10,Bank_Rates!$B$2:$B$100,LOOKUP(2,1/((Bank_Rates!$A$2:$A$100=H10)*(Bank_Rates!$B$2:$B$100<=C10)),Bank_Rates!$B$2:$B$100),Bank_Rates!$D$2:$D$100,_xlfn.AGGREGATE(14,6,Bank_Rates!$D$2:$D$100/((Bank_Rates!$A$2:$A$100=H10)*(Bank_Rates!$B$2:$B$100=LOOKUP(2,1/((Bank_Rates!$A$2:$A$100=H10)*(Bank_Rates!$B$2:$B$100<=C10)),Bank_Rates!$B$2:$B$100))*(Bank_Rates!$D$2:$D$100<=G10)),1)),"No Match") -> 0.02 | K10: =IF(OR(I10="",J10="",J10="No Match"),"",I10-J10) -> 0.047021452
A11: =IF(B11<>"","L-"&TEXT(ROW()-1,"0000"),"") -> L-0010 | B11: TP00558 | C11: 46256 | D11: 50217550 | E11: 50305612 | F11: 46266 | G11: =IF(OR(C11="",F11=""),"",F11-C11) -> 10 | H11: MBB | I11: =IF(OR(D11="",E11="",G11="",G11=0),"",(E11/D11)^(365/G11)-1) -> 0.066039853 | J11: =IFERROR(SUMIFS(Bank_Rates!$C$2:$C$100,Bank_Rates!$A$2:$A$100,H11,Bank_Rates!$B$2:$B$100,LOOKUP(2,1/((Bank_Rates!$A$2:$A$100=H11)*(Bank_Rates!$B$2:$B$100<=C11)),Bank_Rates!$B$2:$B$100),Bank_Rates!$D$2:$D$100,_xlfn.AGGREGATE(14,6,Bank_Rates!$D$2:$D$100/((Bank_Rates!$A$2:$A$100=H11)*(Bank_Rates!$B$2:$B$100=LOOKUP(2,1/((Bank_Rates!$A$2:$A$100=H11)*(Bank_Rates!$B$2:$B$100<=C11)),Bank_Rates!$B$2:$B$100))*(Bank_Rates!$D$2:$D$100<=G11)),1)),"No Match") -> 0.02 | K11: =IF(OR(I11="",J11="",J11="No Match"),"",I11-J11) -> 0.046039853
A12: =IF(B12<>"","L-"&TEXT(ROW()-1,"0000"),"") -> L-0011 | B12: TP00877 | C12: 46256 | D12: 9927097 | E12: 9963029 | F12: 46276 | G12: =IF(OR(C12="",F12=""),"",F12-C12) -> 20 | H12: MBB | I12: =IF(OR(D12="",E12="",G12="",G12=0),"",(E12/D12)^(365/G12)-1) -> 0.06816072 | J12: =IFERROR(SUMIFS(Bank_Rates!$C$2:$C$100,Bank_Rates!$A$2:$A$100,H12,Bank_Rates!$B$2:$B$100,LOOKUP(2,1/((Bank_Rates!$A$2:$A$100=H12)*(Bank_Rates!$B$2:$B$100<=C12)),Bank_Rates!$B$2:$B$100),Bank_Rates!$D$2:$D$100,_xlfn.AGGREGATE(14,6,Bank_Rates!$D$2:$D$100/((Bank_Rates!$A$2:$A$100=H12)*(Bank_Rates!$B$2:$B$100=LOOKUP(2,1/((Bank_Rates!$A$2:$A$100=H12)*(Bank_Rates!$B$2:$B$100<=C12)),Bank_Rates!$B$2:$B$100))*(Bank_Rates!$D$2:$D$100<=G12)),1)),"No Match") -> 0.03 | K12: =IF(OR(I12="",J12="",J12="No Match"),"",I12-J12) -> 0.03816072
A13: =IF(B13<>"","L-"&TEXT(ROW()-1,"0000"),"") -> L-0012 | B13: TP01801 | C13: 46256 | D13: 6557889 | E13: 6584707 | F13: 46269 | G13: =IF(OR(C13="",F13=""),"",F13-C13) -> 13 | H13: MBB | I13: =IF(OR(D13="",E13="",G13="",G13=0),"",(E13/D13)^(365/G13)-1) -> 0.12140724 | J13: =IFERROR(SUMIFS(Bank_Rates!$C$2:$C$100,Bank_Rates!$A$2:$A$100,H13,Bank_Rates!$B$2:$B$100,LOOKUP(2,1/((Bank_Rates!$A$2:$A$100=H13)*(Bank_Rates!$B$2:$B$100<=C13)),Bank_Rates!$B$2:$B$100),Bank_Rates!$D$2:$D$100,_xlfn.AGGREGATE(14,6,Bank_Rates!$D$2:$D$100/((Bank_Rates!$A$2:$A$100=H13)*(Bank_Rates!$B$2:$B$100=LOOKUP(2,1/((Bank_Rates!$A$2:$A$100=H13)*(Bank_Rates!$B$2:$B$100<=C13)),Bank_Rates!$B$2:$B$100))*(Bank_Rates!$D$2:$D$100<=G13)),1)),"No Match") -> 0.02 | K13: =IF(OR(I13="",J13="",J13="No Match"),"",I13-J13) -> 0.10140724
... A45: =IF(B45<>"","L-"&TEXT(ROW()-1,"0000"),"") -> L-0044 | B45: TP78298 | C45: 46308 | D45: 40000000 | E45: 41797721 | F45: 46489 | G45: =IF(OR(C45="",F45=""),"",F45-C45) -> 181 | H45: MBB | I45: =IF(OR(D45="",E45="",G45="",G45=0),"",(E45/D45)^(365/G45)-1) -> 0.092701841 | J45: =IFERROR(SUMIFS(Bank_Rates!$C$2:$C$100,Bank_Rates!$A$2:$A$100,H45,Bank_Rates!$B$2:$B$100,LOOKUP(2,1/((Bank_Rates!$A$2:$A$100=H45)*(Bank_Rates!$B$2:$B$100<=C45)),Bank_Rates!$B$2:$B$100),Bank_Rates!$D$2:$D$100,_xlfn.AGGREGATE(14,6,Bank_Rates!$D$2:$D$100/((Bank_Rates!$A$2:$A$100=H45)*(Bank_Rates!$B$2:$B$100=LOOKUP(2,1/((Bank_Rates!$A$2:$A$100=H45)*(Bank_Rates!$B$2:$B$100<=C45)),Bank_Rates!$B$2:$B$100))*(Bank_Rates!$D$2:$D$100<=G45)),1)),"No Match") -> 0.071 | K45: =IF(OR(I45="",J45="",J45="No Match"),"",I45-J45) -> 0.021701841
A46: =IF(B46<>"","L-"&TEXT(ROW()-1,"0000"),"") | G46: =IF(OR(C46="",F46=""),"",F46-C46) | I46: =IF(OR(D46="",E46="",G46="",G46=0),"",(E46/D46)^(365/G46)-1) | J46: =IFERROR(SUMIFS(Bank_Rates!$C$2:$C$100,Bank_Rates!$A$2:$A$100,H46,Bank_Rates!$B$2:$B$100,LOOKUP(2,1/((Bank_Rates!$A$2:$A$100=H46)*(Bank_Rates!$B$2:$B$100<=C46)),Bank_Rates!$B$2:$B$100),Bank_Rates!$D$2:$D$100,_xlfn.AGGREGATE(14,6,Bank_Rates!$D$2:$D$100/((Bank_Rates!$A$2:$A$100=H46)*(Bank_Rates!$B$2:$B$100=LOOKUP(2,1/((Bank_Rates!$A$2:$A$100=H46)*(Bank_Rates!$B$2:$B$100<=C46)),Bank_Rates!$B$2:$B$100))*(Bank_Rates!$D$2:$D$100<=G46)),1)),"No Match") -> 0 | K46: =IF(OR(I46="",J46="",J46="No Match"),"",I46-J46)
A47: =IF(B47<>"","L-"&TEXT(ROW()-1,"0000"),"") | G47: =IF(OR(C47="",F47=""),"",F47-C47) | I47: =IF(OR(D47="",E47="",G47="",G47=0),"",(E47/D47)^(365/G47)-1) | J47: =IFERROR(SUMIFS(Bank_Rates!$C$2:$C$100,Bank_Rates!$A$2:$A$100,H47,Bank_Rates!$B$2:$B$100,LOOKUP(2,1/((Bank_Rates!$A$2:$A$100=H47)*(Bank_Rates!$B$2:$B$100<=C47)),Bank_Rates!$B$2:$B$100),Bank_Rates!$D$2:$D$100,_xlfn.AGGREGATE(14,6,Bank_Rates!$D$2:$D$100/((Bank_Rates!$A$2:$A$100=H47)*(Bank_Rates!$B$2:$B$100=LOOKUP(2,1/((Bank_Rates!$A$2:$A$100=H47)*(Bank_Rates!$B$2:$B$100<=C47)),Bank_Rates!$B$2:$B$100))*(Bank_Rates!$D$2:$D$100<=G47)),1)),"No Match") -> 0 | K47: =IF(OR(I47="",J47="",J47="No Match"),"",I47-J47)
A48: =IF(B48<>"","L-"&TEXT(ROW()-1,"0000"),"") | G48: =IF(OR(C48="",F48=""),"",F48-C48) | I48: =IF(OR(D48="",E48="",G48="",G48=0),"",(E48/D48)^(365/G48)-1) | J48: =IFERROR(SUMIFS(Bank_Rates!$C$2:$C$100,Bank_Rates!$A$2:$A$100,H48,Bank_Rates!$B$2:$B$100,LOOKUP(2,1/((Bank_Rates!$A$2:$A$100=H48)*(Bank_Rates!$B$2:$B$100<=C48)),Bank_Rates!$B$2:$B$100),Bank_Rates!$D$2:$D$100,_xlfn.AGGREGATE(14,6,Bank_Rates!$D$2:$D$100/((Bank_Rates!$A$2:$A$100=H48)*(Bank_Rates!$B$2:$B$100=LOOKUP(2,1/((Bank_Rates!$A$2:$A$100=H48)*(Bank_Rates!$B$2:$B$100<=C48)),Bank_Rates!$B$2:$B$100))*(Bank_Rates!$D$2:$D$100<=G48)),1)),"No Match") -> 0 | K48: =IF(OR(I48="",J48="",J48="No Match"),"",I48-J48)
A49: =IF(B49<>"","L-"&TEXT(ROW()-1,"0000"),"") | G49: =IF(OR(C49="",F49=""),"",F49-C49) | I49: =IF(OR(D49="",E49="",G49="",G49=0),"",(E49/D49)^(365/G49)-1) | J49: =IFERROR(SUMIFS(Bank_Rates!$C$2:$C$100,Bank_Rates!$A$2:$A$100,H49,Bank_Rates!$B$2:$B$100,LOOKUP(2,1/((Bank_Rates!$A$2:$A$100=H49)*(Bank_Rates!$B$2:$B$100<=C49)),Bank_Rates!$B$2:$B$100),Bank_Rates!$D$2:$D$100,_xlfn.AGGREGATE(14,6,Bank_Rates!$D$2:$D$100/((Bank_Rates!$A$2:$A$100=H49)*(Bank_Rates!$B$2:$B$100=LOOKUP(2,1/((Bank_Rates!$A$2:$A$100=H49)*(Bank_Rates!$B$2:$B$100<=C49)),Bank_Rates!$B$2:$B$100))*(Bank_Rates!$D$2:$D$100<=G49)),1)),"No Match") -> 0 | K49: =IF(OR(I49="",J49="",J49="No Match"),"",I49-J49)
A50: =IF(B50<>"","L-"&TEXT(ROW()-1,"0000"),"") | G50: =IF(OR(C50="",F50=""),"",F50-C50) | I50: =IF(OR(D50="",E50="",G50="",G50=0),"",(E50/D50)^(365/G50)-1) | J50: =IFERROR(SUMIFS(Bank_Rates!$C$2:$C$100,Bank_Rates!$A$2:$A$100,H50,Bank_Rates!$B$2:$B$100,LOOKUP(2,1/((Bank_Rates!$A$2:$A$100=H50)*(Bank_Rates!$B$2:$B$100<=C50)),Bank_Rates!$B$2:$B$100),Bank_Rates!$D$2:$D$100,_xlfn.AGGREGATE(14,6,Bank_Rates!$D$2:$D$100/((Bank_Rates!$A$2:$A$100=H50)*(Bank_Rates!$B$2:$B$100=LOOKUP(2,1/((Bank_Rates!$A$2:$A$100=H50)*(Bank_Rates!$B$2:$B$100<=C50)),Bank_Rates!$B$2:$B$100))*(Bank_Rates!$D$2:$D$100<=G50)),1)),"No Match") -> 0 | K50: =IF(OR(I50="",J50="",J50="No Match"),"",I50-J50)
A51: =IF(B51<>"","L-"&TEXT(ROW()-1,"0000"),"") | G51: =IF(OR(C51="",F51=""),"",F51-C51) | I51: =IF(OR(D51="",E51="",G51="",G51=0),"",(E51/D51)^(365/G51)-1) | J51: =IFERROR(SUMIFS(Bank_Rates!$C$2:$C$100,Bank_Rates!$A$2:$A$100,H51,Bank_Rates!$B$2:$B$100,LOOKUP(2,1/((Bank_Rates!$A$2:$A$100=H51)*(Bank_Rates!$B$2:$B$100<=C51)),Bank_Rates!$B$2:$B$100),Bank_Rates!$D$2:$D$100,_xlfn.AGGREGATE(14,6,Bank_Rates!$D$2:$D$100/((Bank_Rates!$A$2:$A$100=H51)*(Bank_Rates!$B$2:$B$100=LOOKUP(2,1/((Bank_Rates!$A$2:$A$100=H51)*(Bank_Rates!$B$2:$B$100<=C51)),Bank_Rates!$B$2:$B$100))*(Bank_Rates!$D$2:$D$100<=G51)),1)),"No Match") -> 0 | K51: =IF(OR(I51="",J51="",J51="No Match"),"",I51-J51)
A52: =IF(B52<>"","L-"&TEXT(ROW()-1,"0000"),"") | G52: =IF(OR(C52="",F52=""),"",F52-C52) | I52: =IF(OR(D52="",E52="",G52="",G52=0),"",(E52/D52)^(365/G52)-1) | J52: =IFERROR(SUMIFS(Bank_Rates!$C$2:$C$100,Bank_Rates!$A$2:$A$100,H52,Bank_Rates!$B$2:$B$100,LOOKUP(2,1/((Bank_Rates!$A$2:$A$100=H52)*(Bank_Rates!$B$2:$B$100<=C52)),Bank_Rates!$B$2:$B$100),Bank_Rates!$D$2:$D$100,_xlfn.AGGREGATE(14,6,Bank_Rates!$D$2:$D$100/((Bank_Rates!$A$2:$A$100=H52)*(Bank_Rates!$B$2:$B$100=LOOKUP(2,1/((Bank_Rates!$A$2:$A$100=H52)*(Bank_Rates!$B$2:$B$100<=C52)),Bank_Rates!$B$2:$B$100))*(Bank_Rates!$D$2:$D$100<=G52)),1)),"No Match") -> 0 | K52: =IF(OR(I52="",J52="",J52="No Match"),"",I52-J52)
A53: =IF(B53<>"","L-"&TEXT(ROW()-1,"0000"),"") | G53: =IF(OR(C53="",F53=""),"",F53-C53) | I53: =IF(OR(D53="",E53="",G53="",G53=0),"",(E53/D53)^(365/G53)-1) | J53: =IFERROR(SUMIFS(Bank_Rates!$C$2:$C$100,Bank_Rates!$A$2:$A$100,H53,Bank_Rates!$B$2:$B$100,LOOKUP(2,1/((Bank_Rates!$A$2:$A$100=H53)*(Bank_Rates!$B$2:$B$100<=C53)),Bank_Rates!$B$2:$B$100),Bank_Rates!$D$2:$D$100,_xlfn.AGGREGATE(14,6,Bank_Rates!$D$2:$D$100/((Bank_Rates!$A$2:$A$100=H53)*(Bank_Rates!$B$2:$B$100=LOOKUP(2,1/((Bank_Rates!$A$2:$A$100=H53)*(Bank_Rates!$B$2:$B$100<=C53)),Bank_Rates!$B$2:$B$100))*(Bank_Rates!$D$2:$D$100<=G53)),1)),"No Match") -> 0 | K53: =IF(OR(I53="",J53="",J53="No Match"),"",I53-J53)
A54: =IF(B54<>"","L-"&TEXT(ROW()-1,"0000"),"") | G54: =IF(OR(C54="",F54=""),"",F54-C54) | I54: =IF(OR(D54="",E54="",G54="",G54=0),"",(E54/D54)^(365/G54)-1) | J54: =IFERROR(SUMIFS(Bank_Rates!$C$2:$C$100,Bank_Rates!$A$2:$A$100,H54,Bank_Rates!$B$2:$B$100,LOOKUP(2,1/((Bank_Rates!$A$2:$A$100=H54)*(Bank_Rates!$B$2:$B$100<=C54)),Bank_Rates!$B$2:$B$100),Bank_Rates!$D$2:$D$100,_xlfn.AGGREGATE(14,6,Bank_Rates!$D$2:$D$100/((Bank_Rates!$A$2:$A$100=H54)*(Bank_Rates!$B$2:$B$100=LOOKUP(2,1/((Bank_Rates!$A$2:$A$100=H54)*(Bank_Rates!$B$2:$B$100<=C54)),Bank_Rates!$B$2:$B$100))*(Bank_Rates!$D$2:$D$100<=G54)),1)),"No Match") -> 0 | K54: =IF(OR(I54="",J54="",J54="No Match"),"",I54-J54)
A55: =IF(B55<>"","L-"&TEXT(ROW()-1,"0000"),"") | G55: =IF(OR(C55="",F55=""),"",F55-C55) | I55: =IF(OR(D55="",E55="",G55="",G55=0),"",(E55/D55)^(365/G55)-1) | J55: =IFERROR(SUMIFS(Bank_Rates!$C$2:$C$100,Bank_Rates!$A$2:$A$100,H55,Bank_Rates!$B$2:$B$100,LOOKUP(2,1/((Bank_Rates!$A$2:$A$100=H55)*(Bank_Rates!$B$2:$B$100<=C55)),Bank_Rates!$B$2:$B$100),Bank_Rates!$D$2:$D$100,_xlfn.AGGREGATE(14,6,Bank_Rates!$D$2:$D$100/((Bank_Rates!$A$2:$A$100=H55)*(Bank_Rates!$B$2:$B$100=LOOKUP(2,1/((Bank_Rates!$A$2:$A$100=H55)*(Bank_Rates!$B$2:$B$100<=C55)),Bank_Rates!$B$2:$B$100))*(Bank_Rates!$D$2:$D$100<=G55)),1)),"No Match") -> 0 | K55: =IF(OR(I55="",J55="",J55="No Match"),"",I55-J55)
A56: =IF(B56<>"","L-"&TEXT(ROW()-1,"0000"),"") | G56: =IF(OR(C56="",F56=""),"",F56-C56) | I56: =IF(OR(D56="",E56="",G56="",G56=0),"",(E56/D56)^(365/G56)-1) | J56: =IFERROR(SUMIFS(Bank_Rates!$C$2:$C$100,Bank_Rates!$A$2:$A$100,H56,Bank_Rates!$B$2:$B$100,LOOKUP(2,1/((Bank_Rates!$A$2:$A$100=H56)*(Bank_Rates!$B$2:$B$100<=C56)),Bank_Rates!$B$2:$B$100),Bank_Rates!$D$2:$D$100,_xlfn.AGGREGATE(14,6,Bank_Rates!$D$2:$D$100/((Bank_Rates!$A$2:$A$100=H56)*(Bank_Rates!$B$2:$B$100=LOOKUP(2,1/((Bank_Rates!$A$2:$A$100=H56)*(Bank_Rates!$B$2:$B$100<=C56)),Bank_Rates!$B$2:$B$100))*(Bank_Rates!$D$2:$D$100<=G56)),1)),"No Match") -> 0 | K56: =IF(OR(I56="",J56="",J56="No Match"),"",I56-J56)
A57: =IF(B57<>"","L-"&TEXT(ROW()-1,"0000"),"") | G57: =IF(OR(C57="",F57=""),"",F57-C57) | I57: =IF(OR(D57="",E57="",G57="",G57=0),"",(E57/D57)^(365/G57)-1) | J57: =IFERROR(SUMIFS(Bank_Rates!$C$2:$C$100,Bank_Rates!$A$2:$A$100,H57,Bank_Rates!$B$2:$B$100,LOOKUP(2,1/((Bank_Rates!$A$2:$A$100=H57)*(Bank_Rates!$B$2:$B$100<=C57)),Bank_Rates!$B$2:$B$100),Bank_Rates!$D$2:$D$100,_xlfn.AGGREGATE(14,6,Bank_Rates!$D$2:$D$100/((Bank_Rates!$A$2:$A$100=H57)*(Bank_Rates!$B$2:$B$100=LOOKUP(2,1/((Bank_Rates!$A$2:$A$100=H57)*(Bank_Rates!$B$2:$B$100<=C57)),Bank_Rates!$B$2:$B$100))*(Bank_Rates!$D$2:$D$100<=G57)),1)),"No Match") -> 0 | K57: =IF(OR(I57="",J57="",J57="No Match"),"",I57-J57)
... A250: =IF(B250<>"","L-"&TEXT(ROW()-1,"0000"),"") | G250: =IF(OR(C250="",F250=""),"",F250-C250) | I250: =IF(OR(D250="",E250="",G250="",G250=0),"",(E250/D250)^(365/G250)-1) | J250: =IFERROR(SUMIFS(Bank_Rates!$C$2:$C$100,Bank_Rates!$A$2:$A$100,H250,Bank_Rates!$B$2:$B$100,LOOKUP(2,1/((Bank_Rates!$A$2:$A$100=H250)*(Bank_Rates!$B$2:$B$100<=C250)),Bank_Rates!$B$2:$B$100),Bank_Rates!$D$2:$D$100,_xlfn.AGGREGATE(14,6,Bank_Rates!$D$2:$D$100/((Bank_Rates!$A$2:$A$100=H250)*(Bank_Rates!$B$2:$B$100=LOOKUP(2,1/((Bank_Rates!$A$2:$A$100=H250)*(Bank_Rates!$B$2:$B$100<=C250)),Bank_Rates!$B$2:$B$100))*(Bank_Rates!$D$2:$D$100<=G250)),1)),"No Match") -> 0 | K250: =IF(OR(I250="",J250="",J250="No Match"),"",I250-J250)

Sheet Pricing
A1: Listing ID | B1: CD ID | C1: Value at Maturity ($) | D1: Remaining Days | E1: Corresponding Rate | F1: Entry Spread | G1: Liquidity Spread | H1: Pricing Yield | I1: Model Price ($) | J1: Effective Return
A2: L-0001 | B2: TP03077 | C2: =IFERROR(LOOKUP(2,1/((Raw_Observations!$A$2:$A$250=A2)*(Raw_Observations!$B$2:$B$250=B2)),Raw_Observations!$E$2:$E$250),"") -> 4671001 | D2: =IFERROR(MAX(0,LOOKUP(2,1/((Raw_Observations!$A$2:$A$250=A2)*(Raw_Observations!$B$2:$B$250=B2)),Raw_Observations!$F$2:$F$250)-TODAY()),"") -> 0 | E2: =IFERROR(LOOKUP(2,1/((Raw_Observations!$A$2:$A$999=A3)*(Raw_Observations!$B$2:$B$999=B3)),Raw_Observations!$J$2:$J$999),"No Match") -> 0.03 | F2: =IFERROR(LOOKUP(2,1/((Raw_Observations!$A$2:$A$250=A2)*(Raw_Observations!$B$2:$B$250=B2)),Raw_Observations!$K$2:$K$250),"") -> 0.026869531 | G2: 0.02 | H2: =IF(OR(E2="",G2="",E2="No Match"),"",E2+G2) -> 0.05 | I2: =IF(OR(C2="",D2="",H2=""),"",C2/((1+H2)^(D2/365))) -> 4671001 | J2: =IFERROR((I2/LOOKUP(2,1/((Raw_Observations!$A$2:$A$999=A2)*(Raw_Observations!$B$2:$B$999=B2)),Raw_Observations!$D$2:$D$999))^365-1,"") -> 2.8934765
A3: L-0002 | B3: TP03085 | C3: =IFERROR(LOOKUP(2,1/((Raw_Observations!$A$2:$A$250=A3)*(Raw_Observations!$B$2:$B$250=B3)),Raw_Observations!$E$2:$E$250),"") -> 3520202 | D3: =IFERROR(MAX(0,LOOKUP(2,1/((Raw_Observations!$A$2:$A$250=A3)*(Raw_Observations!$B$2:$B$250=B3)),Raw_Observations!$F$2:$F$250)-TODAY()),"") -> 0 | E3: =IFERROR(LOOKUP(2,1/((Raw_Observations!$A$2:$A$999=A4)*(Raw_Observations!$B$2:$B$999=B4)),Raw_Observations!$J$2:$J$999),"No Match") -> 0.03 | F3: =IFERROR(LOOKUP(2,1/((Raw_Observations!$A$2:$A$250=A3)*(Raw_Observations!$B$2:$B$250=B3)),Raw_Observations!$K$2:$K$250),"") -> 0.036845322 | G3: 0.02 | H3: =IF(OR(E3="",G3="",E3="No Match"),"",E3+G3) -> 0.05 | I3: =IF(OR(C3="",D3="",H3=""),"",C3/((1+H3)^(D3/365))) -> 3520202 | J3: =IFERROR((I3/LOOKUP(2,1/((Raw_Observations!$A$2:$A$999=A3)*(Raw_Observations!$B$2:$B$999=B3)),Raw_Observations!$D$2:$D$999))^365-1,"") -> 2.419225
A4: L-0003 | B4: TP03093 | C4: =IFERROR(LOOKUP(2,1/((Raw_Observations!$A$2:$A$250=A4)*(Raw_Observations!$B$2:$B$250=B4)),Raw_Observations!$E$2:$E$250),"") -> 4626551 | D4: =IFERROR(MAX(0,LOOKUP(2,1/((Raw_Observations!$A$2:$A$250=A4)*(Raw_Observations!$B$2:$B$250=B4)),Raw_Observations!$F$2:$F$250)-TODAY()),"") -> 0 | E4: =IFERROR(LOOKUP(2,1/((Raw_Observations!$A$2:$A$999=A4)*(Raw_Observations!$B$2:$B$999=B4)),Raw_Observations!$J$2:$J$999),"No Match") -> 0.03 | F4: =IFERROR(LOOKUP(2,1/((Raw_Observations!$A$2:$A$250=A4)*(Raw_Observations!$B$2:$B$250=B4)),Raw_Observations!$K$2:$K$250),"") -> 0.036879994 | G4: 0.02 | H4: =IF(OR(E4="",G4="",E4="No Match"),"",E4+G4) -> 0.05 | I4: =IF(OR(C4="",D4="",H4=""),"",C4/((1+H4)^(D4/365))) -> 4626551 | J4: =IFERROR((I4/LOOKUP(2,1/((Raw_Observations!$A$2:$A$999=A4)*(Raw_Observations!$B$2:$B$999=B4)),Raw_Observations!$D$2:$D$999))^365-1,"") -> 2.421337
A5: L-0004 | B5: TP03104 | C5: =IFERROR(LOOKUP(2,1/((Raw_Observations!$A$2:$A$250=A5)*(Raw_Observations!$B$2:$B$250=B5)),Raw_Observations!$E$2:$E$250),"") -> 3520202 | D5: =IFERROR(MAX(0,LOOKUP(2,1/((Raw_Observations!$A$2:$A$250=A5)*(Raw_Observations!$B$2:$B$250=B5)),Raw_Observations!$F$2:$F$250)-TODAY()),"") -> 0 | E5: =IFERROR(LOOKUP(2,1/((Raw_Observations!$A$2:$A$999=A5)*(Raw_Observations!$B$2:$B$999=B5)),Raw_Observations!$J$2:$J$999),"No Match") -> 0.03 | F5: =IFERROR(LOOKUP(2,1/((Raw_Observations!$A$2:$A$250=A5)*(Raw_Observations!$B$2:$B$250=B5)),Raw_Observations!$K$2:$K$250),"") -> 0.03631387 | G5: 0.02 | H5: =IF(OR(E5="",G5="",E5="No Match"),"",E5+G5) -> 0.05 | I5: =IF(OR(C5="",D5="",H5=""),"",C5/((1+H5)^(D5/365))) -> 3520202 | J5: =IFERROR((I5/LOOKUP(2,1/((Raw_Observations!$A$2:$A$999=A5)*(Raw_Observations!$B$2:$B$999=B5)),Raw_Observations!$D$2:$D$999))^365-1,"") -> 2.3870071
A6: L-0005 | B6: TP00964 | C6: =IFERROR(LOOKUP(2,1/((Raw_Observations!$A$2:$A$250=A6)*(Raw_Observations!$B$2:$B$250=B6)),Raw_Observations!$E$2:$E$250),"") -> 6749674 | D6: =IFERROR(MAX(0,LOOKUP(2,1/((Raw_Observations!$A$2:$A$250=A6)*(Raw_Observations!$B$2:$B$250=B6)),Raw_Observations!$F$2:$F$250)-TODAY()),"") -> 0 | E6: =IFERROR(LOOKUP(2,1/((Raw_Observations!$A$2:$A$999=A6)*(Raw_Observations!$B$2:$B$999=B6)),Raw_Observations!$J$2:$J$999),"No Match") -> 0.067 | F6: =IFERROR(LOOKUP(2,1/((Raw_Observations!$A$2:$A$250=A6)*(Raw_Observations!$B$2:$B$250=B6)),Raw_Observations!$K$2:$K$250),"") -> 0.0060869004 | G6: 0.002 | H6: =IF(OR(E6="",G6="",E6="No Match"),"",E6+G6) -> 0.069 | I6: =IF(OR(C6="",D6="",H6=""),"",C6/((1+H6)^(D6/365))) -> 6749674 | J6: =IFERROR((I6/LOOKUP(2,1/((Raw_Observations!$A$2:$A$999=A6)*(Raw_Observations!$B$2:$B$999=B6)),Raw_Observations!$D$2:$D$999))^365-1,"") -> 67.880073
A7: L-0006 | B7: TP03429 | C7: =IFERROR(LOOKUP(2,1/((Raw_Observations!$A$2:$A$250=A7)*(Raw_Observations!$B$2:$B$250=B7)),Raw_Observations!$E$2:$E$250),"") -> 20826744 | D7: =IFERROR(MAX(0,LOOKUP(2,1/((Raw_Observations!$A$2:$A$250=A7)*(Raw_Observations!$B$2:$B$250=B7)),Raw_Observations!$F$2:$F$250)-TODAY()),"") -> 122 | E7: =IFERROR(LOOKUP(2,1/((Raw_Observations!$A$2:$A$999=A7)*(Raw_Observations!$B$2:$B$999=B7)),Raw_Observations!$J$2:$J$999),"No Match") -> 0.071 | F7: =IFERROR(LOOKUP(2,1/((Raw_Observations!$A$2:$A$250=A7)*(Raw_Observations!$B$2:$B$250=B7)),Raw_Observations!$K$2:$K$250),"") -> 0.0066851073 | G7: 0.003 | H7: =IF(OR(E7="",G7="",E7="No Match"),"",E7+G7) -> 0.074 | I7: =IF(OR(C7="",D7="",H7=""),"",C7/((1+H7)^(D7/365))) -> 20335661 | J7: =IFERROR((I7/LOOKUP(2,1/((Raw_Observations!$A$2:$A$999=A7)*(Raw_Observations!$B$2:$B$999=B7)),Raw_Observations!$D$2:$D$999))^365-1,"") -> 144.71087
A8: L-0007 | B8: TP00537 | C8: =IFERROR(LOOKUP(2,1/((Raw_Observations!$A$2:$A$250=A8)*(Raw_Observations!$B$2:$B$250=B8)),Raw_Observations!$E$2:$E$250),"") -> 30297331 | D8: =IFERROR(MAX(0,LOOKUP(2,1/((Raw_Observations!$A$2:$A$250=A8)*(Raw_Observations!$B$2:$B$250=B8)),Raw_Observations!$F$2:$F$250)-TODAY()),"") -> 38 | E8: =IFERROR(LOOKUP(2,1/((Raw_Observations!$A$2:$A$999=A8)*(Raw_Observations!$B$2:$B$999=B8)),Raw_Observations!$J$2:$J$999),"No Match") -> 0.07 | F8: =IFERROR(LOOKUP(2,1/((Raw_Observations!$A$2:$A$250=A8)*(Raw_Observations!$B$2:$B$250=B8)),Raw_Observations!$K$2:$K$250),"") -> 0.0089830705 | G8: 0.0034 | H8: =IF(OR(E8="",G8="",E8="No Match"),"",E8+G8) -> 0.0734 | I8: =IF(OR(C8="",D8="",H8=""),"",C8/((1+H8)^(D8/365))) -> 30074734 | J8: =IFERROR((I8/LOOKUP(2,1/((Raw_Observations!$A$2:$A$999=A8)*(Raw_Observations!$B$2:$B$999=B8)),Raw_Observations!$D$2:$D$999))^365-1,"") -> 115.54492
A9: L-0008 | B9: TP01034 | C9: =IFERROR(LOOKUP(2,1/((Raw_Observations!$A$2:$A$250=A9)*(Raw_Observations!$B$2:$B$250=B9)),Raw_Observations!$E$2:$E$250),"") -> 31206091 | D9: =IFERROR(MAX(0,LOOKUP(2,1/((Raw_Observations!$A$2:$A$250=A9)*(Raw_Observations!$B$2:$B$250=B9)),Raw_Observations!$F$2:$F$250)-TODAY()),"") -> 123 | E9: =IFERROR(LOOKUP(2,1/((Raw_Observations!$A$2:$A$999=A9)*(Raw_Observations!$B$2:$B$999=B9)),Raw_Observations!$J$2:$J$999),"No Match") -> 0.071 | F9: =IFERROR(LOOKUP(2,1/((Raw_Observations!$A$2:$A$250=A9)*(Raw_Observations!$B$2:$B$250=B9)),Raw_Observations!$K$2:$K$250),"") -> 0.0074884785 | G9: 0.003 | H9: =IF(OR(E9="",G9="",E9="No Match"),"",E9+G9) -> 0.074 | I9: =IF(OR(C9="",D9="",H9=""),"",C9/((1+H9)^(D9/365))) -> 30464310 | J9: =IFERROR((I9/LOOKUP(2,1/((Raw_Observations!$A$2:$A$999=A9)*(Raw_Observations!$B$2:$B$999=B9)),Raw_Observations!$D$2:$D$999))^365-1,"") -> 154.49331
A10: L-0009 | B10: TP00945 | C10: =IFERROR(LOOKUP(2,1/((Raw_Observations!$A$2:$A$250=A10)*(Raw_Observations!$B$2:$B$250=B10)),Raw_Observations!$E$2:$E$250),"") -> 20110411 | D10: =IFERROR(MAX(0,LOOKUP(2,1/((Raw_Observations!$A$2:$A$250=A10)*(Raw_Observations!$B$2:$B$250=B10)),Raw_Observations!$F$2:$F$250)-TODAY()),"") -> 0 | E10: =IFERROR(LOOKUP(2,1/((Raw_Observations!$A$2:$A$999=A10)*(Raw_Observations!$B$2:$B$999=B10)),Raw_Observations!$J$2:$J$999),"No Match") -> 0.02 | F10: =IFERROR(LOOKUP(2,1/((Raw_Observations!$A$2:$A$250=A10)*(Raw_Observations!$B$2:$B$250=B10)),Raw_Observations!$K$2:$K$250),"") -> 0.047021452 | G10: 0.01 | H10: =IF(OR(E10="",G10="",E10="No Match"),"",E10+G10) -> 0.03 | I10: =IF(OR(C10="",D10="",H10=""),"",C10/((1+H10)^(D10/365))) -> 20110411 | J10: =IFERROR((I10/LOOKUP(2,1/((Raw_Observations!$A$2:$A$999=A10)*(Raw_Observations!$B$2:$B$999=B10)),Raw_Observations!$D$2:$D$999))^365-1,"") -> 1.3240794
A11: L-0010 | B11: TP00558 | C11: =IFERROR(LOOKUP(2,1/((Raw_Observations!$A$2:$A$250=A11)*(Raw_Observations!$B$2:$B$250=B11)),Raw_Observations!$E$2:$E$250),"") -> 50305612 | D11: =IFERROR(MAX(0,LOOKUP(2,1/((Raw_Observations!$A$2:$A$250=A11)*(Raw_Observations!$B$2:$B$250=B11)),Raw_Observations!$F$2:$F$250)-TODAY()),"") -> 0 | E11: =IFERROR(LOOKUP(2,1/((Raw_Observations!$A$2:$A$999=A11)*(Raw_Observations!$B$2:$B$999=B11)),Raw_Observations!$J$2:$J$999),"No Match") -> 0.02 | F11: =IFERROR(LOOKUP(2,1/((Raw_Observations!$A$2:$A$250=A11)*(Raw_Observations!$B$2:$B$250=B11)),Raw_Observations!$K$2:$K$250),"") -> 0.046039853 | G11: 0.017 | H11: =IF(OR(E11="",G11="",E11="No Match"),"",E11+G11) -> 0.037 | I11: =IF(OR(C11="",D11="",H11=""),"",C11/((1+H11)^(D11/365))) -> 50305612 | J11: =IFERROR((I11/LOOKUP(2,1/((Raw_Observations!$A$2:$A$999=A11)*(Raw_Observations!$B$2:$B$999=B11)),Raw_Observations!$D$2:$D$999))^365-1,"") -> 0.89554635
A12: L-0011 | B12: TP00877 | C12: =IFERROR(LOOKUP(2,1/((Raw_Observations!$A$2:$A$250=A12)*(Raw_Observations!$B$2:$B$250=B12)),Raw_Observations!$E$2:$E$250),"") -> 9963029 | D12: =IFERROR(MAX(0,LOOKUP(2,1/((Raw_Observations!$A$2:$A$250=A12)*(Raw_Observations!$B$2:$B$250=B12)),Raw_Observations!$F$2:$F$250)-TODAY()),"") -> 0 | E12: =IFERROR(LOOKUP(2,1/((Raw_Observations!$A$2:$A$999=A12)*(Raw_Observations!$B$2:$B$999=B12)),Raw_Observations!$J$2:$J$999),"No Match") -> 0.03 | F12: =IFERROR(LOOKUP(2,1/((Raw_Observations!$A$2:$A$250=A12)*(Raw_Observations!$B$2:$B$250=B12)),Raw_Observations!$K$2:$K$250),"") -> 0.03816072 | G12: 0.017 | H12: =IF(OR(E12="",G12="",E12="No Match"),"",E12+G12) -> 0.047 | I12: =IF(OR(C12="",D12="",H12=""),"",C12/((1+H12)^(D12/365))) -> 9963029 | J12: =IFERROR((I12/LOOKUP(2,1/((Raw_Observations!$A$2:$A$999=A12)*(Raw_Observations!$B$2:$B$999=B12)),Raw_Observations!$D$2:$D$999))^365-1,"") -> 2.7387986
A13: L-0012 | B13: TP01801 | C13: =IFERROR(LOOKUP(2,1/((Raw_Observations!$A$2:$A$250=A13)*(Raw_Observations!$B$2:$B$250=B13)),Raw_Observations!$E$2:$E$250),"") -> 6584707 | D13: =IFERROR(MAX(0,LOOKUP(2,1/((Raw_Observations!$A$2:$A$250=A13)*(Raw_Observations!$B$2:$B$250=B13)),Raw_Observations!$F$2:$F$250)-TODAY()),"") -> 0 | E13: =IFERROR(LOOKUP(2,1/((Raw_Observations!$A$2:$A$999=A13)*(Raw_Observations!$B$2:$B$999=B13)),Raw_Observations!$J$2:$J$999),"No Match") -> 0.02 | F13: =IFERROR(LOOKUP(2,1/((Raw_Observations!$A$2:$A$250=A13)*(Raw_Observations!$B$2:$B$250=B13)),Raw_Observations!$K$2:$K$250),"") -> 0.10140724 | G13: 0.017 | H13: =IF(OR(E13="",G13="",E13="No Match"),"",E13+G13) -> 0.037 | I13: =IF(OR(C13="",D13="",H13=""),"",C13/((1+H13)^(D13/365))) -> 6584707 | J13: =IFERROR((I13/LOOKUP(2,1/((Raw_Observations!$A$2:$A$999=A13)*(Raw_Observations!$B$2:$B$999=B13)),Raw_Observations!$D$2:$D$999))^365-1,"") -> 3.4353062
A14: L-0013 | B14: TP00397 | C14: =IFERROR(LOOKUP(2,1/((Raw_Observations!$A$2:$A$250=A14)*(Raw_Observations!$B$2:$B$250=B14)),Raw_Observations!$E$2:$E$250),"") -> 4574570 | D14: =IFERROR(MAX(0,LOOKUP(2,1/((Raw_Observations!$A$2:$A$250=A14)*(Raw_Observations!$B$2:$B$250=B14)),Raw_Observations!$F$2:$F$250)-TODAY()),"") -> 0 | E14: =IFERROR(LOOKUP(2,1/((Raw_Observations!$A$2:$A$999=A14)*(Raw_Observations!$B$2:$B$999=B14)),Raw_Observations!$J$2:$J$999),"No Match") -> 0.04 | F14: =IFERROR(LOOKUP(2,1/((Raw_Observations!$A$2:$A$250=A14)*(Raw_Observations!$B$2:$B$250=B14)),Raw_Observations!$K$2:$K$250),"") -> 0.026926527 | G14: 0.017 | H14: =IF(OR(E14="",G14="",E14="No Match"),"",E14+G14) -> 0.057 | I14: =IF(OR(C14="",D14="",H14=""),"",C14/((1+H14)^(D14/365))) -> 4574570 | J14: =IFERROR((I14/LOOKUP(2,1/((Raw_Observations!$A$2:$A$999=A14)*(Raw_Observations!$B$2:$B$999=B14)),Raw_Observations!$D$2:$D$999))^365-1,"") -> 4.0508309
A15: L-0014 | B15: TP93098 | C15: =IFERROR(LOOKUP(2,1/((Raw_Observations!$A$2:$A$250=A15)*(Raw_Observations!$B$2:$B$250=B15)),Raw_Observations!$E$2:$E$250),"") -> 51993393 | D15: =IFERROR(MAX(0,LOOKUP(2,1/((Raw_Observations!$A$2:$A$250=A15)*(Raw_Observations!$B$2:$B$250=B15)),Raw_Observations!$F$2:$F$250)-TODAY()),"") -> 131 | E15: =IFERROR(LOOKUP(2,1/((Raw_Observations!$A$2:$A$999=A15)*(Raw_Observations!$B$2:$B$999=B15)),Raw_Observations!$J$2:$J$999),"No Match") -> 0.071 | F15: =IFERROR(LOOKUP(2,1/((Raw_Observations!$A$2:$A$250=A15)*(Raw_Observations!$B$2:$B$250=B15)),Raw_Observations!$K$2:$K$250),"") -> 0.011432327 | G15: 0.0093 | H15: =IF(OR(E15="",G15="",E15="No Match"),"",E15+G15) -> 0.0803 | I15: =IF(OR(C15="",D15="",H15=""),"",C15/((1+H15)^(D15/365))) -> 50571862 | J15: =IFERROR((I15/LOOKUP(2,1/((Raw_Observations!$A$2:$A$999=A15)*(Raw_Observations!$B$2:$B$999=B15)),Raw_Observations!$D$2:$D$999))^365-1,"") -> 78.620473
... A22: L-0021 | B22: TP00665 | C22: =IFERROR(LOOKUP(2,1/((Raw_Observations!$A$2:$A$250=A22)*(Raw_Observations!$B$2:$B$250=B22)),Raw_Observations!$E$2:$E$250),"") -> 15030272 | D22: =IFERROR(MAX(0,LOOKUP(2,1/((Raw_Observations!$A$2:$A$250=A22)*(Raw_Observations!$B$2:$B$250=B22)),Raw_Observations!$F$2:$F$250)-TODAY()),"") -> 0 | E22: =IFERROR(LOOKUP(2,1/((Raw_Observations!$A$2:$A$999=A22)*(Raw_Observations!$B$2:$B$999=B22)),Raw_Observations!$J$2:$J$999),"No Match") -> 0.03 | F22: =IFERROR(LOOKUP(2,1/((Raw_Observations!$A$2:$A$250=A22)*(Raw_Observations!$B$2:$B$250=B22)),Raw_Observations!$K$2:$K$250),"") -> 0.031642019 | G22: 0.0295 | H22: =IF(OR(E22="",G22="",E22="No Match"),"",E22+G22) -> 0.0595 | I22: =IF(OR(C22="",D22="",H22=""),"",C22/((1+H22)^(D22/365))) -> 15030272 | J22: =IFERROR((I22/LOOKUP(2,1/((Raw_Observations!$A$2:$A$999=A22)*(Raw_Observations!$B$2:$B$999=B22)),Raw_Observations!$D$2:$D$999))^365-1,"") -> 1.9349843
A23: L-0025 | B23: TP51686 | C23: =IFERROR(LOOKUP(2,1/((Raw_Observations!$A$2:$A$250=A23)*(Raw_Observations!$B$2:$B$250=B23)),Raw_Observations!$E$2:$E$250),"") -> 52225917 | D23: =IFERROR(MAX(0,LOOKUP(2,1/((Raw_Observations!$A$2:$A$250=A23)*(Raw_Observations!$B$2:$B$250=B23)),Raw_Observations!$F$2:$F$250)-TODAY()),"") -> 179 | E23: =IFERROR(LOOKUP(2,1/((Raw_Observations!$A$2:$A$999=A24)*(Raw_Observations!$B$2:$B$999=B24)),Raw_Observations!$J$2:$J$999),"No Match") -> 0.071 | F23: =IFERROR(LOOKUP(2,1/((Raw_Observations!$A$2:$A$250=A23)*(Raw_Observations!$B$2:$B$250=B23)),Raw_Observations!$K$2:$K$250),"") -> 0.022053441 | G23: 0.0208 | H23: =IF(OR(E23="",G23="",E23="No Match"),"",E23+G23) -> 0.0918 | I23: =IF(OR(C23="",D23="",H23=""),"",C23/((1+H23)^(D23/365))) -> 50024215 | J23: =IFERROR((I23/LOOKUP(2,1/((Raw_Observations!$A$2:$A$999=A23)*(Raw_Observations!$B$2:$B$999=B23)),Raw_Observations!$D$2:$D$999))^365-1,"") -> 0.34226459
A24: L-0026 | B24: TP03038 | C24: =IFERROR(LOOKUP(2,1/((Raw_Observations!$A$2:$A$250=A24)*(Raw_Observations!$B$2:$B$250=B24)),Raw_Observations!$E$2:$E$250),"") -> 52242252 | D24: =IFERROR(MAX(0,LOOKUP(2,1/((Raw_Observations!$A$2:$A$250=A24)*(Raw_Observations!$B$2:$B$250=B24)),Raw_Observations!$F$2:$F$250)-TODAY()),"") -> 179 | E24: =IFERROR(LOOKUP(2,1/((Raw_Observations!$A$2:$A$999=A25)*(Raw_Observations!$B$2:$B$999=B25)),Raw_Observations!$J$2:$J$999),"No Match") -> 0.071 | F24: =IFERROR(LOOKUP(2,1/((Raw_Observations!$A$2:$A$250=A24)*(Raw_Observations!$B$2:$B$250=B24)),Raw_Observations!$K$2:$K$250),"") -> 0.022076615 | G24: 0.0208 | H24: =IF(OR(E24="",G24="",E24="No Match"),"",E24+G24) -> 0.0918 | I24: =IF(OR(C24="",D24="",H24=""),"",C24/((1+H24)^(D24/365))) -> 50039862 | J24: =IFERROR((I24/LOOKUP(2,1/((Raw_Observations!$A$2:$A$999=A24)*(Raw_Observations!$B$2:$B$999=B24)),Raw_Observations!$D$2:$D$999))^365-1,"") -> 0.34739661
A25: L-0027 | B25: TP00403 | C25: =IFERROR(LOOKUP(2,1/((Raw_Observations!$A$2:$A$250=A25)*(Raw_Observations!$B$2:$B$250=B25)),Raw_Observations!$E$2:$E$250),"") -> 52372315 | D25: =IFERROR(MAX(0,LOOKUP(2,1/((Raw_Observations!$A$2:$A$250=A25)*(Raw_Observations!$B$2:$B$250=B25)),Raw_Observations!$F$2:$F$250)-TODAY()),"") -> 180 | E25: =IFERROR(LOOKUP(2,1/((Raw_Observations!$A$2:$A$999=A26)*(Raw_Observations!$B$2:$B$999=B26)),Raw_Observations!$J$2:$J$999),"No Match") -> 0.071 | F25: =IFERROR(LOOKUP(2,1/((Raw_Observations!$A$2:$A$250=A25)*(Raw_Observations!$B$2:$B$250=B25)),Raw_Observations!$K$2:$K$250),"") -> 0.021969745 | G25: 0.0208 | H25: =IF(OR(E25="",G25="",E25="No Match"),"",E25+G25) -> 0.0918 | I25: =IF(OR(C25="",D25="",H25=""),"",C25/((1+H25)^(D25/365))) -> 50152372 | J25: =IFERROR((I25/LOOKUP(2,1/((Raw_Observations!$A$2:$A$999=A25)*(Raw_Observations!$B$2:$B$999=B25)),Raw_Observations!$D$2:$D$999))^365-1,"") -> 0.32530912
A26: L-0028 | B26: TP96004 | C26: =IFERROR(LOOKUP(2,1/((Raw_Observations!$A$2:$A$250=A26)*(Raw_Observations!$B$2:$B$250=B26)),Raw_Observations!$E$2:$E$250),"") -> 52295424 | D26: =IFERROR(MAX(0,LOOKUP(2,1/((Raw_Observations!$A$2:$A$250=A26)*(Raw_Observations!$B$2:$B$250=B26)),Raw_Observations!$F$2:$F$250)-TODAY()),"") -> 179 | E26: =IFERROR(LOOKUP(2,1/((Raw_Observations!$A$2:$A$999=A27)*(Raw_Observations!$B$2:$B$999=B27)),Raw_Observations!$J$2:$J$999),"No Match") -> 0.071 | F26: =IFERROR(LOOKUP(2,1/((Raw_Observations!$A$2:$A$250=A26)*(Raw_Observations!$B$2:$B$250=B26)),Raw_Observations!$K$2:$K$250),"") -> 0.021983125 | G26: 0.0208 | H26: =IF(OR(E26="",G26="",E26="No Match"),"",E26+G26) -> 0.0918 | I26: =IF(OR(C26="",D26="",H26=""),"",C26/((1+H26)^(D26/365))) -> 50090792 | J26: =IFERROR((I26/LOOKUP(2,1/((Raw_Observations!$A$2:$A$999=A26)*(Raw_Observations!$B$2:$B$999=B26)),Raw_Observations!$D$2:$D$999))^365-1,"") -> 0.32681112
A27: L-0029 | B27: TP51250 | C27: =IFERROR(LOOKUP(2,1/((Raw_Observations!$A$2:$A$250=A27)*(Raw_Observations!$B$2:$B$250=B27)),Raw_Observations!$E$2:$E$250),"") -> 52266726 | D27: =IFERROR(MAX(0,LOOKUP(2,1/((Raw_Observations!$A$2:$A$250=A27)*(Raw_Observations!$B$2:$B$250=B27)),Raw_Observations!$F$2:$F$250)-TODAY()),"") -> 180 | E27: =IFERROR(LOOKUP(2,1/((Raw_Observations!$A$2:$A$999=A28)*(Raw_Observations!$B$2:$B$999=B28)),Raw_Observations!$J$2:$J$999),"No Match") -> 0.071 | F27: =IFERROR(LOOKUP(2,1/((Raw_Observations!$A$2:$A$250=A27)*(Raw_Observations!$B$2:$B$250=B27)),Raw_Observations!$K$2:$K$250),"") -> 0.021939763 | G27: 0.0208 | H27: =IF(OR(E27="",G27="",E27="No Match"),"",E27+G27) -> 0.0918 | I27: =IF(OR(C27="",D27="",H27=""),"",C27/((1+H27)^(D27/365))) -> 50051259 | J27: =IFERROR((I27/LOOKUP(2,1/((Raw_Observations!$A$2:$A$999=A27)*(Raw_Observations!$B$2:$B$999=B27)),Raw_Observations!$D$2:$D$999))^365-1,"") -> 0.3187451
A28: L-0030 | B28: TP22853 | C28: =IFERROR(LOOKUP(2,1/((Raw_Observations!$A$2:$A$250=A28)*(Raw_Observations!$B$2:$B$250=B28)),Raw_Observations!$E$2:$E$250),"") -> 52256593 | D28: =IFERROR(MAX(0,LOOKUP(2,1/((Raw_Observations!$A$2:$A$250=A28)*(Raw_Observations!$B$2:$B$250=B28)),Raw_Observations!$F$2:$F$250)-TODAY()),"") -> 180 | E28: =IFERROR(LOOKUP(2,1/((Raw_Observations!$A$2:$A$999=A29)*(Raw_Observations!$B$2:$B$999=B29)),Raw_Observations!$J$2:$J$999),"No Match") -> 0.071 | F28: =IFERROR(LOOKUP(2,1/((Raw_Observations!$A$2:$A$250=A28)*(Raw_Observations!$B$2:$B$250=B28)),Raw_Observations!$K$2:$K$250),"") -> 0.022055997 | G28: 0.02198 | H28: =IF(OR(E28="",G28="",E28="No Match"),"",E28+G28) -> 0.09298 | I28: =IF(OR(C28="",D28="",H28=""),"",C28/((1+H28)^(D28/365))) -> 50014905 | J28: =IFERROR((I28/LOOKUP(2,1/((Raw_Observations!$A$2:$A$999=A28)*(Raw_Observations!$B$2:$B$999=B28)),Raw_Observations!$D$2:$D$999))^365-1,"") -> 0.10682192
A29: L-0031 | B29: TP01183 | C29: =IFERROR(LOOKUP(2,1/((Raw_Observations!$A$2:$A$250=A29)*(Raw_Observations!$B$2:$B$250=B29)),Raw_Observations!$E$2:$E$250),"") -> 34463041 | D29: =IFERROR(MAX(0,LOOKUP(2,1/((Raw_Observations!$A$2:$A$250=A29)*(Raw_Observations!$B$2:$B$250=B29)),Raw_Observations!$F$2:$F$250)-TODAY()),"") -> 179 | E29: =IFERROR(LOOKUP(2,1/((Raw_Observations!$A$2:$A$999=A30)*(Raw_Observations!$B$2:$B$999=B30)),Raw_Observations!$J$2:$J$999),"No Match") -> 0.071 | F29: =IFERROR(LOOKUP(2,1/((Raw_Observations!$A$2:$A$250=A29)*(Raw_Observations!$B$2:$B$250=B29)),Raw_Observations!$K$2:$K$250),"") -> 0.021889685 | G29: 0.0208 | H29: =IF(OR(E29="",G29="",E29="No Match"),"",E29+G29) -> 0.0918 | I29: =IF(OR(C29="",D29="",H29=""),"",C29/((1+H29)^(D29/365))) -> 33010174 | J29: =IFERROR((I29/LOOKUP(2,1/((Raw_Observations!$A$2:$A$999=A29)*(Raw_Observations!$B$2:$B$999=B29)),Raw_Observations!$D$2:$D$999))^365-1,"") -> 0.30654915
A30: L-0032 | B30: TP03921 | C30: =IFERROR(LOOKUP(2,1/((Raw_Observations!$A$2:$A$250=A30)*(Raw_Observations!$B$2:$B$250=B30)),Raw_Observations!$E$2:$E$250),"") -> 34443606 | D30: =IFERROR(MAX(0,LOOKUP(2,1/((Raw_Observations!$A$2:$A$250=A30)*(Raw_Observations!$B$2:$B$250=B30)),Raw_Observations!$F$2:$F$250)-TODAY()),"") -> 179 | E30: =IFERROR(LOOKUP(2,1/((Raw_Observations!$A$2:$A$999=A31)*(Raw_Observations!$B$2:$B$999=B31)),Raw_Observations!$J$2:$J$999),"No Match") -> 0.071 | F30: =IFERROR(LOOKUP(2,1/((Raw_Observations!$A$2:$A$250=A30)*(Raw_Observations!$B$2:$B$250=B30)),Raw_Observations!$K$2:$K$250),"") -> 0.021849216 | G30: 0.0208 | H30: =IF(OR(E30="",G30="",E30="No Match"),"",E30+G30) -> 0.0918 | I30: =IF(OR(C30="",D30="",H30=""),"",C30/((1+H30)^(D30/365))) -> 32991558 | J30: =IFERROR((I30/LOOKUP(2,1/((Raw_Observations!$A$2:$A$999=A30)*(Raw_Observations!$B$2:$B$999=B30)),Raw_Observations!$D$2:$D$999))^365-1,"") -> 0.29786935
A31: L-0033 | B31: TP00975 | C31: =IFERROR(LOOKUP(2,1/((Raw_Observations!$A$2:$A$250=A31)*(Raw_Observations!$B$2:$B$250=B31)),Raw_Observations!$E$2:$E$250),"") -> 34475656 | D31: =IFERROR(MAX(0,LOOKUP(2,1/((Raw_Observations!$A$2:$A$250=A31)*(Raw_Observations!$B$2:$B$250=B31)),Raw_Observations!$F$2:$F$250)-TODAY()),"") -> 179 | E31: 0.071 | F31: =IFERROR(LOOKUP(2,1/((Raw_Observations!$A$2:$A$250=A31)*(Raw_Observations!$B$2:$B$250=B31)),Raw_Observations!$K$2:$K$250),"") -> 0.02176037 | G31: 0.0208 | H31: =IF(OR(E31="",G31="",E31="No Match"),"",E31+G31) -> 0.0918 | I31: =IF(OR(C31="",D31="",H31=""),"",C31/((1+H31)^(D31/365))) -> 33022257 | J31: =IFERROR((I31/LOOKUP(2,1/((Raw_Observations!$A$2:$A$999=A31)*(Raw_Observations!$B$2:$B$999=B31)),Raw_Observations!$D$2:$D$999))^365-1,"") -> 0.27901444
C32: =IFERROR(LOOKUP(2,1/((Raw_Observations!$A$2:$A$250=A32)*(Raw_Observations!$B$2:$B$250=B32)),Raw_Observations!$E$2:$E$250),"") -> 0 | D32: =IFERROR(MAX(0,LOOKUP(2,1/((Raw_Observations!$A$2:$A$250=A32)*(Raw_Observations!$B$2:$B$250=B32)),Raw_Observations!$F$2:$F$250)-TODAY()),"") -> 0 | E32: =IFERROR(LOOKUP(2,1/((Raw_Observations!$A$2:$A$999=A33)*(Raw_Observations!$B$2:$B$999=B33)),Raw_Observations!$J$2:$J$999),"No Match") -> 0 | F32: =IFERROR(LOOKUP(2,1/((Raw_Observations!$A$2:$A$250=A32)*(Raw_Observations!$B$2:$B$250=B32)),Raw_Observations!$K$2:$K$250),"") | H32: =IF(OR(E32="",G32="",E32="No Match"),"",E32+G32) | I32: =IF(OR(C32="",D32="",H32=""),"",C32/((1+H32)^(D32/365))) | J32: =IFERROR((I32/LOOKUP(2,1/((Raw_Observations!$A$2:$A$999=A32)*(Raw_Observations!$B$2:$B$999=B32)),Raw_Observations!$D$2:$D$999))^365-1,"")
C33: =IFERROR(LOOKUP(2,1/((Raw_Observations!$A$2:$A$250=A33)*(Raw_Observations!$B$2:$B$250=B33)),Raw_Observations!$E$2:$E$250),"") -> 0 | D33: =IFERROR(MAX(0,LOOKUP(2,1/((Raw_Observations!$A$2:$A$250=A33)*(Raw_Observations!$B$2:$B$250=B33)),Raw_Observations!$F$2:$F$250)-TODAY()),"") -> 0 | E33: =IF(OR(A33="",B33=""),"",IFERROR(SUMIFS(Bank_Rates!$C$2:$C$100,Bank_Rates!$A$2:$A$100,LOOKUP(2,1/((Raw_Observations!$A$2:$A$250=A33)*(Raw_Observations!$B$2:$B$250=B33)),Raw_Observations!$H$2:$H$250),Bank_Rates!$B$2:$B$100,MAXIFS(Bank_Rates!$B$2:$B$100,Bank_Rates!$A$2:$A$100,LOOKUP(2,1/((Raw_Observations!$A$2:$A$250=A33)*(Raw_Observations!$B$2:$B$250=B33)),Raw_Observations!$H$2:$H$250),Bank_Rates!$B$2:$B$100,"<="&TODAY()),Bank_Rates!$D$2:$D$100,MAXIFS(Bank_Rates!$D$2:$D$100,Bank_Rates!$A$2:$A$100,LOOKUP(2,1/((Raw_Observations!$A$2:$A$250=A33)*(Raw_Observations!$B$2:$B$250=B33)),Raw_Observations!$H$2:$H$250),Bank_Rates!$B$2:$B$100,MAXIFS(Bank_Rates!$B$2:$B$100,Bank_Rates!$A$2:$A$100,LOOKUP(2,1/((Raw_Observations!$A$2:$A$250=A33)*(Raw_Observations!$B$2:$B$250=B33)),Raw_Observations!$H$2:$H$250),Bank_Rates!$B$2:$B$100,"<="&TODAY()),Bank_Rates!$D$2:$D$100,"<="&D33)),"No Match")) | F33: =IFERROR(LOOKUP(2,1/((Raw_Observations!$A$2:$A$250=A33)*(Raw_Observations!$B$2:$B$250=B33)),Raw_Observations!$K$2:$K$250),"") | H33: =IF(OR(E33="",G33="",E33="No Match"),"",E33+G33) | I33: =IF(OR(C33="",D33="",H33=""),"",C33/((1+H33)^(D33/365))) | J33: =IFERROR((I33/LOOKUP(2,1/((Raw_Observations!$A$2:$A$999=A33)*(Raw_Observations!$B$2:$B$999=B33)),Raw_Observations!$D$2:$D$999))^365-1,"")
C34: =IFERROR(LOOKUP(2,1/((Raw_Observations!$A$2:$A$250=A34)*(Raw_Observations!$B$2:$B$250=B34)),Raw_Observations!$E$2:$E$250),"") -> 0 | D34: =IFERROR(MAX(0,LOOKUP(2,1/((Raw_Observations!$A$2:$A$250=A34)*(Raw_Observations!$B$2:$B$250=B34)),Raw_Observations!$F$2:$F$250)-TODAY()),"") -> 0 | E34: =IF(OR(A34="",B34=""),"",IFERROR(SUMIFS(Bank_Rates!$C$2:$C$100,Bank_Rates!$A$2:$A$100,LOOKUP(2,1/((Raw_Observations!$A$2:$A$250=A34)*(Raw_Observations!$B$2:$B$250=B34)),Raw_Observations!$H$2:$H$250),Bank_Rates!$B$2:$B$100,MAXIFS(Bank_Rates!$B$2:$B$100,Bank_Rates!$A$2:$A$100,LOOKUP(2,1/((Raw_Observations!$A$2:$A$250=A34)*(Raw_Observations!$B$2:$B$250=B34)),Raw_Observations!$H$2:$H$250),Bank_Rates!$B$2:$B$100,"<="&TODAY()),Bank_Rates!$D$2:$D$100,MAXIFS(Bank_Rates!$D$2:$D$100,Bank_Rates!$A$2:$A$100,LOOKUP(2,1/((Raw_Observations!$A$2:$A$250=A34)*(Raw_Observations!$B$2:$B$250=B34)),Raw_Observations!$H$2:$H$250),Bank_Rates!$B$2:$B$100,MAXIFS(Bank_Rates!$B$2:$B$100,Bank_Rates!$A$2:$A$100,LOOKUP(2,1/((Raw_Observations!$A$2:$A$250=A34)*(Raw_Observations!$B$2:$B$250=B34)),Raw_Observations!$H$2:$H$250),Bank_Rates!$B$2:$B$100,"<="&TODAY()),Bank_Rates!$D$2:$D$100,"<="&D34)),"No Match")) | F34: =IFERROR(LOOKUP(2,1/((Raw_Observations!$A$2:$A$250=A34)*(Raw_Observations!$B$2:$B$250=B34)),Raw_Observations!$K$2:$K$250),"") | H34: =IF(OR(E34="",G34="",E34="No Match"),"",E34+G34) | I34: =IF(OR(C34="",D34="",H34=""),"",C34/((1+H34)^(D34/365))) | J34: =IFERROR((I34/LOOKUP(2,1/((Raw_Observations!$A$2:$A$999=A34)*(Raw_Observations!$B$2:$B$999=B34)),Raw_Observations!$D$2:$D$999))^365-1,"")
C35: =IFERROR(LOOKUP(2,1/((Raw_Observations!$A$2:$A$250=A35)*(Raw_Observations!$B$2:$B$250=B35)),Raw_Observations!$E$2:$E$250),"") -> 0 | D35: =IFERROR(MAX(0,LOOKUP(2,1/((Raw_Observations!$A$2:$A$250=A35)*(Raw_Observations!$B$2:$B$250=B35)),Raw_Observations!$F$2:$F$250)-TODAY()),"") -> 0 | E35: =IF(OR(A35="",B35=""),"",IFERROR(SUMIFS(Bank_Rates!$C$2:$C$100,Bank_Rates!$A$2:$A$100,LOOKUP(2,1/((Raw_Observations!$A$2:$A$250=A35)*(Raw_Observations!$B$2:$B$250=B35)),Raw_Observations!$H$2:$H$250),Bank_Rates!$B$2:$B$100,MAXIFS(Bank_Rates!$B$2:$B$100,Bank_Rates!$A$2:$A$100,LOOKUP(2,1/((Raw_Observations!$A$2:$A$250=A35)*(Raw_Observations!$B$2:$B$250=B35)),Raw_Observations!$H$2:$H$250),Bank_Rates!$B$2:$B$100,"<="&TODAY()),Bank_Rates!$D$2:$D$100,MAXIFS(Bank_Rates!$D$2:$D$100,Bank_Rates!$A$2:$A$100,LOOKUP(2,1/((Raw_Observations!$A$2:$A$250=A35)*(Raw_Observations!$B$2:$B$250=B35)),Raw_Observations!$H$2:$H$250),Bank_Rates!$B$2:$B$100,MAXIFS(Bank_Rates!$B$2:$B$100,Bank_Rates!$A$2:$A$100,LOOKUP(2,1/((Raw_Observations!$A$2:$A$250=A35)*(Raw_Observations!$B$2:$B$250=B35)),Raw_Observations!$H$2:$H$250),Bank_Rates!$B$2:$B$100,"<="&TODAY()),Bank_Rates!$D$2:$D$100,"<="&D35)),"No Match")) | F35: =IFERROR(LOOKUP(2,1/((Raw_Observations!$A$2:$A$250=A35)*(Raw_Observations!$B$2:$B$250=B35)),Raw_Observations!$K$2:$K$250),"") | H35: =IF(OR(E35="",G35="",E35="No Match"),"",E35+G35) | I35: =IF(OR(C35="",D35="",H35=""),"",C35/((1+H35)^(D35/365))) | J35: =IFERROR((I35/LOOKUP(2,1/((Raw_Observations!$A$2:$A$999=A35)*(Raw_Observations!$B$2:$B$999=B35)),Raw_Observations!$D$2:$D$999))^365-1,"")
C36: =IFERROR(LOOKUP(2,1/((Raw_Observations!$A$2:$A$250=A36)*(Raw_Observations!$B$2:$B$250=B36)),Raw_Observations!$E$2:$E$250),"") -> 0 | D36: =IFERROR(MAX(0,LOOKUP(2,1/((Raw_Observations!$A$2:$A$250=A36)*(Raw_Observations!$B$2:$B$250=B36)),Raw_Observations!$F$2:$F$250)-TODAY()),"") -> 0 | E36: =IF(OR(A36="",B36=""),"",IFERROR(SUMIFS(Bank_Rates!$C$2:$C$100,Bank_Rates!$A$2:$A$100,LOOKUP(2,1/((Raw_Observations!$A$2:$A$250=A36)*(Raw_Observations!$B$2:$B$250=B36)),Raw_Observations!$H$2:$H$250),Bank_Rates!$B$2:$B$100,MAXIFS(Bank_Rates!$B$2:$B$100,Bank_Rates!$A$2:$A$100,LOOKUP(2,1/((Raw_Observations!$A$2:$A$250=A36)*(Raw_Observations!$B$2:$B$250=B36)),Raw_Observations!$H$2:$H$250),Bank_Rates!$B$2:$B$100,"<="&TODAY()),Bank_Rates!$D$2:$D$100,MAXIFS(Bank_Rates!$D$2:$D$100,Bank_Rates!$A$2:$A$100,LOOKUP(2,1/((Raw_Observations!$A$2:$A$250=A36)*(Raw_Observations!$B$2:$B$250=B36)),Raw_Observations!$H$2:$H$250),Bank_Rates!$B$2:$B$100,MAXIFS(Bank_Rates!$B$2:$B$100,Bank_Rates!$A$2:$A$100,LOOKUP(2,1/((Raw_Observations!$A$2:$A$250=A36)*(Raw_Observations!$B$2:$B$250=B36)),Raw_Observations!$H$2:$H$250),Bank_Rates!$B$2:$B$100,"<="&TODAY()),Bank_Rates!$D$2:$D$100,"<="&D36)),"No Match")) | F36: =IFERROR(LOOKUP(2,1/((Raw_Observations!$A$2:$A$250=A36)*(Raw_Observations!$B$2:$B$250=B36)),Raw_Observations!$K$2:$K$250),"") | H36: =IF(OR(E36="",G36="",E36="No Match"),"",E36+G36) | I36: =IF(OR(C36="",D36="",H36=""),"",C36/((1+H36)^(D36/365))) | J36: =IFERROR((I36/LOOKUP(2,1/((Raw_Observations!$A$2:$A$999=A36)*(Raw_Observations!$B$2:$B$999=B36)),Raw_Observations!$D$2:$D$999))^365-1,"")
C37: =IFERROR(LOOKUP(2,1/((Raw_Observations!$A$2:$A$250=A37)*(Raw_Observations!$B$2:$B$250=B37)),Raw_Observations!$E$2:$E$250),"") -> 0 | D37: =IFERROR(MAX(0,LOOKUP(2,1/((Raw_Observations!$A$2:$A$250=A37)*(Raw_Observations!$B$2:$B$250=B37)),Raw_Observations!$F$2:$F$250)-TODAY()),"") -> 0 | E37: =IF(OR(A37="",B37=""),"",IFERROR(SUMIFS(Bank_Rates!$C$2:$C$100,Bank_Rates!$A$2:$A$100,LOOKUP(2,1/((Raw_Observations!$A$2:$A$250=A37)*(Raw_Observations!$B$2:$B$250=B37)),Raw_Observations!$H$2:$H$250),Bank_Rates!$B$2:$B$100,MAXIFS(Bank_Rates!$B$2:$B$100,Bank_Rates!$A$2:$A$100,LOOKUP(2,1/((Raw_Observations!$A$2:$A$250=A37)*(Raw_Observations!$B$2:$B$250=B37)),Raw_Observations!$H$2:$H$250),Bank_Rates!$B$2:$B$100,"<="&TODAY()),Bank_Rates!$D$2:$D$100,MAXIFS(Bank_Rates!$D$2:$D$100,Bank_Rates!$A$2:$A$100,LOOKUP(2,1/((Raw_Observations!$A$2:$A$250=A37)*(Raw_Observations!$B$2:$B$250=B37)),Raw_Observations!$H$2:$H$250),Bank_Rates!$B$2:$B$100,MAXIFS(Bank_Rates!$B$2:$B$100,Bank_Rates!$A$2:$A$100,LOOKUP(2,1/((Raw_Observations!$A$2:$A$250=A37)*(Raw_Observations!$B$2:$B$250=B37)),Raw_Observations!$H$2:$H$250),Bank_Rates!$B$2:$B$100,"<="&TODAY()),Bank_Rates!$D$2:$D$100,"<="&D37)),"No Match")) | F37: =IFERROR(LOOKUP(2,1/((Raw_Observations!$A$2:$A$250=A37)*(Raw_Observations!$B$2:$B$250=B37)),Raw_Observations!$K$2:$K$250),"") | H37: =IF(OR(E37="",G37="",E37="No Match"),"",E37+G37) | I37: =IF(OR(C37="",D37="",H37=""),"",C37/((1+H37)^(D37/365))) | J37: =IFERROR((I37/LOOKUP(2,1/((Raw_Observations!$A$2:$A$999=A37)*(Raw_Observations!$B$2:$B$999=B37)),Raw_Observations!$D$2:$D$999))^365-1,"")
C38: =IFERROR(LOOKUP(2,1/((Raw_Observations!$A$2:$A$250=A38)*(Raw_Observations!$B$2:$B$250=B38)),Raw_Observations!$E$2:$E$250),"") -> 0 | D38: =IFERROR(MAX(0,LOOKUP(2,1/((Raw_Observations!$A$2:$A$250=A38)*(Raw_Observations!$B$2:$B$250=B38)),Raw_Observations!$F$2:$F$250)-TODAY()),"") -> 0 | E38: =IF(OR(A38="",B38=""),"",IFERROR(SUMIFS(Bank_Rates!$C$2:$C$100,Bank_Rates!$A$2:$A$100,LOOKUP(2,1/((Raw_Observations!$A$2:$A$250=A38)*(Raw_Observations!$B$2:$B$250=B38)),Raw_Observations!$H$2:$H$250),Bank_Rates!$B$2:$B$100,MAXIFS(Bank_Rates!$B$2:$B$100,Bank_Rates!$A$2:$A$100,LOOKUP(2,1/((Raw_Observations!$A$2:$A$250=A38)*(Raw_Observations!$B$2:$B$250=B38)),Raw_Observations!$H$2:$H$250),Bank_Rates!$B$2:$B$100,"<="&TODAY()),Bank_Rates!$D$2:$D$100,MAXIFS(Bank_Rates!$D$2:$D$100,Bank_Rates!$A$2:$A$100,LOOKUP(2,1/((Raw_Observations!$A$2:$A$250=A38)*(Raw_Observations!$B$2:$B$250=B38)),Raw_Observations!$H$2:$H$250),Bank_Rates!$B$2:$B$100,MAXIFS(Bank_Rates!$B$2:$B$100,Bank_Rates!$A$2:$A$100,LOOKUP(2,1/((Raw_Observations!$A$2:$A$250=A38)*(Raw_Observations!$B$2:$B$250=B38)),Raw_Observations!$H$2:$H$250),Bank_Rates!$B$2:$B$100,"<="&TODAY()),Bank_Rates!$D$2:$D$100,"<="&D38)),"No Match")) | F38: =IFERROR(LOOKUP(2,1/((Raw_Observations!$A$2:$A$250=A38)*(Raw_Observations!$B$2:$B$250=B38)),Raw_Observations!$K$2:$K$250),"") | H38: =IF(OR(E38="",G38="",E38="No Match"),"",E38+G38) | I38: =IF(OR(C38="",D38="",H38=""),"",C38/((1+H38)^(D38/365))) | J38: =IFERROR((I38/LOOKUP(2,1/((Raw_Observations!$A$2:$A$999=A38)*(Raw_Observations!$B$2:$B$999=B38)),Raw_Observations!$D$2:$D$999))^365-1,"")
C39: =IFERROR(LOOKUP(2,1/((Raw_Observations!$A$2:$A$250=A39)*(Raw_Observations!$B$2:$B$250=B39)),Raw_Observations!$E$2:$E$250),"") -> 0 | D39: =IFERROR(MAX(0,LOOKUP(2,1/((Raw_Observations!$A$2:$A$250=A39)*(Raw_Observations!$B$2:$B$250=B39)),Raw_Observations!$F$2:$F$250)-TODAY()),"") -> 0 | E39: =IF(OR(A39="",B39=""),"",IFERROR(SUMIFS(Bank_Rates!$C$2:$C$100,Bank_Rates!$A$2:$A$100,LOOKUP(2,1/((Raw_Observations!$A$2:$A$250=A39)*(Raw_Observations!$B$2:$B$250=B39)),Raw_Observations!$H$2:$H$250),Bank_Rates!$B$2:$B$100,MAXIFS(Bank_Rates!$B$2:$B$100,Bank_Rates!$A$2:$A$100,LOOKUP(2,1/((Raw_Observations!$A$2:$A$250=A39)*(Raw_Observations!$B$2:$B$250=B39)),Raw_Observations!$H$2:$H$250),Bank_Rates!$B$2:$B$100,"<="&TODAY()),Bank_Rates!$D$2:$D$100,MAXIFS(Bank_Rates!$D$2:$D$100,Bank_Rates!$A$2:$A$100,LOOKUP(2,1/((Raw_Observations!$A$2:$A$250=A39)*(Raw_Observations!$B$2:$B$250=B39)),Raw_Observations!$H$2:$H$250),Bank_Rates!$B$2:$B$100,MAXIFS(Bank_Rates!$B$2:$B$100,Bank_Rates!$A$2:$A$100,LOOKUP(2,1/((Raw_Observations!$A$2:$A$250=A39)*(Raw_Observations!$B$2:$B$250=B39)),Raw_Observations!$H$2:$H$250),Bank_Rates!$B$2:$B$100,"<="&TODAY()),Bank_Rates!$D$2:$D$100,"<="&D39)),"No Match")) | F39: =IFERROR(LOOKUP(2,1/((Raw_Observations!$A$2:$A$250=A39)*(Raw_Observations!$B$2:$B$250=B39)),Raw_Observations!$K$2:$K$250),"") | H39: =IF(OR(E39="",G39="",E39="No Match"),"",E39+G39) | I39: =IF(OR(C39="",D39="",H39=""),"",C39/((1+H39)^(D39/365))) | J39: =IFERROR((I39/LOOKUP(2,1/((Raw_Observations!$A$2:$A$999=A39)*(Raw_Observations!$B$2:$B$999=B39)),Raw_Observations!$D$2:$D$999))^365-1,"")
C40: =IFERROR(LOOKUP(2,1/((Raw_Observations!$A$2:$A$250=A40)*(Raw_Observations!$B$2:$B$250=B40)),Raw_Observations!$E$2:$E$250),"") -> 0 | D40: =IFERROR(MAX(0,LOOKUP(2,1/((Raw_Observations!$A$2:$A$250=A40)*(Raw_Observations!$B$2:$B$250=B40)),Raw_Observations!$F$2:$F$250)-TODAY()),"") -> 0 | E40: =IF(OR(A40="",B40=""),"",IFERROR(SUMIFS(Bank_Rates!$C$2:$C$100,Bank_Rates!$A$2:$A$100,LOOKUP(2,1/((Raw_Observations!$A$2:$A$250=A40)*(Raw_Observations!$B$2:$B$250=B40)),Raw_Observations!$H$2:$H$250),Bank_Rates!$B$2:$B$100,MAXIFS(Bank_Rates!$B$2:$B$100,Bank_Rates!$A$2:$A$100,LOOKUP(2,1/((Raw_Observations!$A$2:$A$250=A40)*(Raw_Observations!$B$2:$B$250=B40)),Raw_Observations!$H$2:$H$250),Bank_Rates!$B$2:$B$100,"<="&TODAY()),Bank_Rates!$D$2:$D$100,MAXIFS(Bank_Rates!$D$2:$D$100,Bank_Rates!$A$2:$A$100,LOOKUP(2,1/((Raw_Observations!$A$2:$A$250=A40)*(Raw_Observations!$B$2:$B$250=B40)),Raw_Observations!$H$2:$H$250),Bank_Rates!$B$2:$B$100,MAXIFS(Bank_Rates!$B$2:$B$100,Bank_Rates!$A$2:$A$100,LOOKUP(2,1/((Raw_Observations!$A$2:$A$250=A40)*(Raw_Observations!$B$2:$B$250=B40)),Raw_Observations!$H$2:$H$250),Bank_Rates!$B$2:$B$100,"<="&TODAY()),Bank_Rates!$D$2:$D$100,"<="&D40)),"No Match")) | F40: =IFERROR(LOOKUP(2,1/((Raw_Observations!$A$2:$A$250=A40)*(Raw_Observations!$B$2:$B$250=B40)),Raw_Observations!$K$2:$K$250),"") | H40: =IF(OR(E40="",G40="",E40="No Match"),"",E40+G40) | I40: =IF(OR(C40="",D40="",H40=""),"",C40/((1+H40)^(D40/365))) | J40: =IFERROR((I40/LOOKUP(2,1/((Raw_Observations!$A$2:$A$999=A40)*(Raw_Observations!$B$2:$B$999=B40)),Raw_Observations!$D$2:$D$999))^365-1,"")
C41: =IFERROR(LOOKUP(2,1/((Raw_Observations!$A$2:$A$250=A41)*(Raw_Observations!$B$2:$B$250=B41)),Raw_Observations!$E$2:$E$250),"") -> 0 | D41: =IFERROR(MAX(0,LOOKUP(2,1/((Raw_Observations!$A$2:$A$250=A41)*(Raw_Observations!$B$2:$B$250=B41)),Raw_Observations!$F$2:$F$250)-TODAY()),"") -> 0 | E41: =IF(OR(A41="",B41=""),"",IFERROR(SUMIFS(Bank_Rates!$C$2:$C$100,Bank_Rates!$A$2:$A$100,LOOKUP(2,1/((Raw_Observations!$A$2:$A$250=A41)*(Raw_Observations!$B$2:$B$250=B41)),Raw_Observations!$H$2:$H$250),Bank_Rates!$B$2:$B$100,MAXIFS(Bank_Rates!$B$2:$B$100,Bank_Rates!$A$2:$A$100,LOOKUP(2,1/((Raw_Observations!$A$2:$A$250=A41)*(Raw_Observations!$B$2:$B$250=B41)),Raw_Observations!$H$2:$H$250),Bank_Rates!$B$2:$B$100,"<="&TODAY()),Bank_Rates!$D$2:$D$100,MAXIFS(Bank_Rates!$D$2:$D$100,Bank_Rates!$A$2:$A$100,LOOKUP(2,1/((Raw_Observations!$A$2:$A$250=A41)*(Raw_Observations!$B$2:$B$250=B41)),Raw_Observations!$H$2:$H$250),Bank_Rates!$B$2:$B$100,MAXIFS(Bank_Rates!$B$2:$B$100,Bank_Rates!$A$2:$A$100,LOOKUP(2,1/((Raw_Observations!$A$2:$A$250=A41)*(Raw_Observations!$B$2:$B$250=B41)),Raw_Observations!$H$2:$H$250),Bank_Rates!$B$2:$B$100,"<="&TODAY()),Bank_Rates!$D$2:$D$100,"<="&D41)),"No Match")) | F41: =IFERROR(LOOKUP(2,1/((Raw_Observations!$A$2:$A$250=A41)*(Raw_Observations!$B$2:$B$250=B41)),Raw_Observations!$K$2:$K$250),"") | H41: =IF(OR(E41="",G41="",E41="No Match"),"",E41+G41) | I41: =IF(OR(C41="",D41="",H41=""),"",C41/((1+H41)^(D41/365))) | J41: =IFERROR((I41/LOOKUP(2,1/((Raw_Observations!$A$2:$A$999=A41)*(Raw_Observations!$B$2:$B$999=B41)),Raw_Observations!$D$2:$D$999))^365-1,"")
C42: =IFERROR(LOOKUP(2,1/((Raw_Observations!$A$2:$A$250=A42)*(Raw_Observations!$B$2:$B$250=B42)),Raw_Observations!$E$2:$E$250),"") -> 0 | D42: =IFERROR(MAX(0,LOOKUP(2,1/((Raw_Observations!$A$2:$A$250=A42)*(Raw_Observations!$B$2:$B$250=B42)),Raw_Observations!$F$2:$F$250)-TODAY()),"") -> 0 | E42: =IF(OR(A42="",B42=""),"",IFERROR(SUMIFS(Bank_Rates!$C$2:$C$100,Bank_Rates!$A$2:$A$100,LOOKUP(2,1/((Raw_Observations!$A$2:$A$250=A42)*(Raw_Observations!$B$2:$B$250=B42)),Raw_Observations!$H$2:$H$250),Bank_Rates!$B$2:$B$100,MAXIFS(Bank_Rates!$B$2:$B$100,Bank_Rates!$A$2:$A$100,LOOKUP(2,1/((Raw_Observations!$A$2:$A$250=A42)*(Raw_Observations!$B$2:$B$250=B42)),Raw_Observations!$H$2:$H$250),Bank_Rates!$B$2:$B$100,"<="&TODAY()),Bank_Rates!$D$2:$D$100,MAXIFS(Bank_Rates!$D$2:$D$100,Bank_Rates!$A$2:$A$100,LOOKUP(2,1/((Raw_Observations!$A$2:$A$250=A42)*(Raw_Observations!$B$2:$B$250=B42)),Raw_Observations!$H$2:$H$250),Bank_Rates!$B$2:$B$100,MAXIFS(Bank_Rates!$B$2:$B$100,Bank_Rates!$A$2:$A$100,LOOKUP(2,1/((Raw_Observations!$A$2:$A$250=A42)*(Raw_Observations!$B$2:$B$250=B42)),Raw_Observations!$H$2:$H$250),Bank_Rates!$B$2:$B$100,"<="&TODAY()),Bank_Rates!$D$2:$D$100,"<="&D42)),"No Match")) | F42: =IFERROR(LOOKUP(2,1/((Raw_Observations!$A$2:$A$250=A42)*(Raw_Observations!$B$2:$B$250=B42)),Raw_Observations!$K$2:$K$250),"") | H42: =IF(OR(E42="",G42="",E42="No Match"),"",E42+G42) | I42: =IF(OR(C42="",D42="",H42=""),"",C42/((1+H42)^(D42/365))) | J42: =IFERROR((I42/LOOKUP(2,1/((Raw_Observations!$A$2:$A$999=A42)*(Raw_Observations!$B$2:$B$999=B42)),Raw_Observations!$D$2:$D$999))^365-1,"")
C43: =IFERROR(LOOKUP(2,1/((Raw_Observations!$A$2:$A$250=A43)*(Raw_Observations!$B$2:$B$250=B43)),Raw_Observations!$E$2:$E$250),"") -> 0 | D43: =IFERROR(MAX(0,LOOKUP(2,1/((Raw_Observations!$A$2:$A$250=A43)*(Raw_Observations!$B$2:$B$250=B43)),Raw_Observations!$F$2:$F$250)-TODAY()),"") -> 0 | E43: =IF(OR(A43="",B43=""),"",IFERROR(SUMIFS(Bank_Rates!$C$2:$C$100,Bank_Rates!$A$2:$A$100,LOOKUP(2,1/((Raw_Observations!$A$2:$A$250=A43)*(Raw_Observations!$B$2:$B$250=B43)),Raw_Observations!$H$2:$H$250),Bank_Rates!$B$2:$B$100,MAXIFS(Bank_Rates!$B$2:$B$100,Bank_Rates!$A$2:$A$100,LOOKUP(2,1/((Raw_Observations!$A$2:$A$250=A43)*(Raw_Observations!$B$2:$B$250=B43)),Raw_Observations!$H$2:$H$250),Bank_Rates!$B$2:$B$100,"<="&TODAY()),Bank_Rates!$D$2:$D$100,MAXIFS(Bank_Rates!$D$2:$D$100,Bank_Rates!$A$2:$A$100,LOOKUP(2,1/((Raw_Observations!$A$2:$A$250=A43)*(Raw_Observations!$B$2:$B$250=B43)),Raw_Observations!$H$2:$H$250),Bank_Rates!$B$2:$B$100,MAXIFS(Bank_Rates!$B$2:$B$100,Bank_Rates!$A$2:$A$100,LOOKUP(2,1/((Raw_Observations!$A$2:$A$250=A43)*(Raw_Observations!$B$2:$B$250=B43)),Raw_Observations!$H$2:$H$250),Bank_Rates!$B$2:$B$100,"<="&TODAY()),Bank_Rates!$D$2:$D$100,"<="&D43)),"No Match")) | F43: =IFERROR(LOOKUP(2,1/((Raw_Observations!$A$2:$A$250=A43)*(Raw_Observations!$B$2:$B$250=B43)),Raw_Observations!$K$2:$K$250),"") | H43: =IF(OR(E43="",G43="",E43="No Match"),"",E43+G43) | I43: =IF(OR(C43="",D43="",H43=""),"",C43/((1+H43)^(D43/365))) | J43: =IFERROR((I43/LOOKUP(2,1/((Raw_Observations!$A$2:$A$999=A43)*(Raw_Observations!$B$2:$B$999=B43)),Raw_Observations!$D$2:$D$999))^365-1,"")
C44: =IFERROR(LOOKUP(2,1/((Raw_Observations!$A$2:$A$250=A44)*(Raw_Observations!$B$2:$B$250=B44)),Raw_Observations!$E$2:$E$250),"") -> 0 | D44: =IFERROR(MAX(0,LOOKUP(2,1/((Raw_Observations!$A$2:$A$250=A44)*(Raw_Observations!$B$2:$B$250=B44)),Raw_Observations!$F$2:$F$250)-TODAY()),"") -> 0 | E44: =IF(OR(A44="",B44=""),"",IFERROR(SUMIFS(Bank_Rates!$C$2:$C$100,Bank_Rates!$A$2:$A$100,LOOKUP(2,1/((Raw_Observations!$A$2:$A$250=A44)*(Raw_Observations!$B$2:$B$250=B44)),Raw_Observations!$H$2:$H$250),Bank_Rates!$B$2:$B$100,MAXIFS(Bank_Rates!$B$2:$B$100,Bank_Rates!$A$2:$A$100,LOOKUP(2,1/((Raw_Observations!$A$2:$A$250=A44)*(Raw_Observations!$B$2:$B$250=B44)),Raw_Observations!$H$2:$H$250),Bank_Rates!$B$2:$B$100,"<="&TODAY()),Bank_Rates!$D$2:$D$100,MAXIFS(Bank_Rates!$D$2:$D$100,Bank_Rates!$A$2:$A$100,LOOKUP(2,1/((Raw_Observations!$A$2:$A$250=A44)*(Raw_Observations!$B$2:$B$250=B44)),Raw_Observations!$H$2:$H$250),Bank_Rates!$B$2:$B$100,MAXIFS(Bank_Rates!$B$2:$B$100,Bank_Rates!$A$2:$A$100,LOOKUP(2,1/((Raw_Observations!$A$2:$A$250=A44)*(Raw_Observations!$B$2:$B$250=B44)),Raw_Observations!$H$2:$H$250),Bank_Rates!$B$2:$B$100,"<="&TODAY()),Bank_Rates!$D$2:$D$100,"<="&D44)),"No Match")) | F44: =IFERROR(LOOKUP(2,1/((Raw_Observations!$A$2:$A$250=A44)*(Raw_Observations!$B$2:$B$250=B44)),Raw_Observations!$K$2:$K$250),"") | H44: =IF(OR(E44="",G44="",E44="No Match"),"",E44+G44) | I44: =IF(OR(C44="",D44="",H44=""),"",C44/((1+H44)^(D44/365))) | J44: =IFERROR((I44/LOOKUP(2,1/((Raw_Observations!$A$2:$A$999=A44)*(Raw_Observations!$B$2:$B$999=B44)),Raw_Observations!$D$2:$D$999))^365-1,"")
... C200: =IFERROR(LOOKUP(2,1/((Raw_Observations!$A$2:$A$250=A200)*(Raw_Observations!$B$2:$B$250=B200)),Raw_Observations!$E$2:$E$250),"") -> 0 | D200: =IFERROR(MAX(0,LOOKUP(2,1/((Raw_Observations!$A$2:$A$250=A200)*(Raw_Observations!$B$2:$B$250=B200)),Raw_Observations!$F$2:$F$250)-TODAY()),"") -> 0 | E200: =IF(OR(A200="",B200=""),"",IFERROR(SUMIFS(Bank_Rates!$C$2:$C$100,Bank_Rates!$A$2:$A$100,LOOKUP(2,1/((Raw_Observations!$A$2:$A$250=A200)*(Raw_Observations!$B$2:$B$250=B200)),Raw_Observations!$H$2:$H$250),Bank_Rates!$B$2:$B$100,MAXIFS(Bank_Rates!$B$2:$B$100,Bank_Rates!$A$2:$A$100,LOOKUP(2,1/((Raw_Observations!$A$2:$A$250=A200)*(Raw_Observations!$B$2:$B$250=B200)),Raw_Observations!$H$2:$H$250),Bank_Rates!$B$2:$B$100,"<="&TODAY()),Bank_Rates!$D$2:$D$100,MAXIFS(Bank_Rates!$D$2:$D$100,Bank_Rates!$A$2:$A$100,LOOKUP(2,1/((Raw_Observations!$A$2:$A$250=A200)*(Raw_Observations!$B$2:$B$250=B200)),Raw_Observations!$H$2:$H$250),Bank_Rates!$B$2:$B$100,MAXIFS(Bank_Rates!$B$2:$B$100,Bank_Rates!$A$2:$A$100,LOOKUP(2,1/((Raw_Observations!$A$2:$A$250=A200)*(Raw_Observations!$B$2:$B$250=B200)),Raw_Observations!$H$2:$H$250),Bank_Rates!$B$2:$B$100,"<="&TODAY()),Bank_Rates!$D$2:$D$100,"<="&D200)),"No Match")) | F200: =IFERROR(LOOKUP(2,1/((Raw_Observations!$A$2:$A$250=A200)*(Raw_Observations!$B$2:$B$250=B200)),Raw_Observations!$K$2:$K$250),"") | H200: =IF(OR(E200="",G200="",E200="No Match"),"",E200+G200) | I200: =IF(OR(C200="",D200="",H200=""),"",C200/((1+H200)^(D200/365))) | J200: =IFERROR((I200/LOOKUP(2,1/((Raw_Observations!$A$2:$A$999=A200)*(Raw_Observations!$B$2:$B$999=B200)),Raw_Observations!$D$2:$D$999))^365-1,"")

Sheet Buy_History
A1: Listing ID | B1: CD ID | C1: Buy Timestamp | D1: Parent Listing ID | E1: Face Value ($) | F1: Remaining Face Value ($)
A2: L-0001 | B2: TP03077 | C2: 46253 | F2: =IF(E2="","",MAX(0,E2-SUMIFS($E:$E,$D:$D,A2)-SUMIFS(Sell_History!$E:$E,Sell_History!$A:$A,A2,Sell_History!$B:$B,B2)))
A3: L-0002 | B3: TP03085 | C3: 46253 | F3: =IF(E3="","",MAX(0,E3-SUMIFS($E:$E,$D:$D,A3)-SUMIFS(Sell_History!$E:$E,Sell_History!$A:$A,A3,Sell_History!$B:$B,B3)))
A4: L-0003 | B4: TP03093 | C4: 46253 | F4: =IF(E4="","",MAX(0,E4-SUMIFS($E:$E,$D:$D,A4)-SUMIFS(Sell_History!$E:$E,Sell_History!$A:$A,A4,Sell_History!$B:$B,B4)))
A5: L-0004 | B5: TP03104 | C5: 46253 | F5: =IF(E5="","",MAX(0,E5-SUMIFS($E:$E,$D:$D,A5)-SUMIFS(Sell_History!$E:$E,Sell_History!$A:$A,A5,Sell_History!$B:$B,B5)))
A6: L-0005 | B6: TP00964 | C6: 46245 | F6: =IF(E6="","",MAX(0,E6-SUMIFS($E:$E,$D:$D,A6)-SUMIFS(Sell_History!$E:$E,Sell_History!$A:$A,A6,Sell_History!$B:$B,B6)))
A7: L-0006 | B7: TP03429 | C7: 46247 | F7: =IF(E7="","",MAX(0,E7-SUMIFS($E:$E,$D:$D,A7)-SUMIFS(Sell_History!$E:$E,Sell_History!$A:$A,A7,Sell_History!$B:$B,B7)))
A8: L-0007 | B8: TP00537 | C8: 46248 | F8: =IF(E8="","",MAX(0,E8-SUMIFS($E:$E,$D:$D,A8)-SUMIFS(Sell_History!$E:$E,Sell_History!$A:$A,A8,Sell_History!$B:$B,B8)))
A9: L-0008 | B9: TP01034 | C9: 46248 | F9: =IF(E9="","",MAX(0,E9-SUMIFS($E:$E,$D:$D,A9)-SUMIFS(Sell_History!$E:$E,Sell_History!$A:$A,A9,Sell_History!$B:$B,B9)))
A10: L-0009 | B10: TP00945 | C10: 46251 | F10: =IF(E10="","",MAX(0,E10-SUMIFS($E:$E,$D:$D,A10)-SUMIFS(Sell_History!$E:$E,Sell_History!$A:$A,A10,Sell_History!$B:$B,B10)))
A11: L-0010 | B11: TP00558 | C11: 46256 | F11: =IF(E11="","",MAX(0,E11-SUMIFS($E:$E,$D:$D,A11)-SUMIFS(Sell_History!$E:$E,Sell_History!$A:$A,A11,Sell_History!$B:$B,B11)))
A12: L-0015 | B12: TP01953 | C12: 46257 | F12: =IF(E12="","",MAX(0,E12-SUMIFS($E:$E,$D:$D,A12)-SUMIFS(Sell_History!$E:$E,Sell_History!$A:$A,A12,Sell_History!$B:$B,B12)))
A13: L-0016 | B13: TP01959 | C13: 46257 | F13: =IF(E13="","",MAX(0,E13-SUMIFS($E:$E,$D:$D,A13)-SUMIFS(Sell_History!$E:$E,Sell_History!$A:$A,A13,Sell_History!$B:$B,B13)))
... A15: L-0018 | B15: TP01114 | C15: 46258 | F15: =IF(E15="","",MAX(0,E15-SUMIFS($E:$E,$D:$D,A15)-SUMIFS(Sell_History!$E:$E,Sell_History!$A:$A,A15,Sell_History!$B:$B,B15)))
A16: L-0019 | B16: TP00575 | C16: 46262 | E16: 45000000 | F16: =IF(E16="","",MAX(0,E16-SUMIFS($E:$E,$D:$D,A16)-SUMIFS(Sell_History!$E:$E,Sell_History!$A:$A,A16,Sell_History!$B:$B,B16))) -> 0
A17: L-00191 | B17: TP00575 | C17: 46269 | D17: L-0019 | E17: 22000000 | F17: =IF(E17="","",MAX(0,E17-SUMIFS($E:$E,$D:$D,A17)-SUMIFS(Sell_History!$E:$E,Sell_History!$A:$A,A17,Sell_History!$B:$B,B17))) -> 0
A18: L-00192 | B18: TP00575 | C18: 46271 | D18: L-0019 | E18: 23000000 | F18: =IF(E18="","",MAX(0,E18-SUMIFS($E:$E,$D:$D,A18)-SUMIFS(Sell_History!$E:$E,Sell_History!$A:$A,A18,Sell_History!$B:$B,B18))) -> 0
A19: L-0020 | B19: TP00658 | C19: 46280 | F19: =IF(E19="","",MAX(0,E19-SUMIFS($E:$E,$D:$D,A19)-SUMIFS(Sell_History!$E:$E,Sell_History!$A:$A,A19,Sell_History!$B:$B,B19)))
A20: L-0021 | B20: TP00665 | C20: 46280 | F20: =IF(E20="","",MAX(0,E20-SUMIFS($E:$E,$D:$D,A20)-SUMIFS(Sell_History!$E:$E,Sell_History!$A:$A,A20,Sell_History!$B:$B,B20)))
A21: L-0022 | B21: TP60268 | C21: 46282 | F21: =IF(E21="","",MAX(0,E21-SUMIFS($E:$E,$D:$D,A21)-SUMIFS(Sell_History!$E:$E,Sell_History!$A:$A,A21,Sell_History!$B:$B,B21)))
A22: L-0030 | B22: TP22853 | C22: 46307 | F22: =IF(E22="","",MAX(0,E22-SUMIFS($E:$E,$D:$D,A22)-SUMIFS(Sell_History!$E:$E,Sell_History!$A:$A,A22,Sell_History!$B:$B,B22)))
F23: =IF(E23="","",MAX(0,E23-SUMIFS($E:$E,$D:$D,A23)-SUMIFS(Sell_History!$E:$E,Sell_History!$A:$A,A23,Sell_History!$B:$B,B23)))
F24: =IF(E24="","",MAX(0,E24-SUMIFS($E:$E,$D:$D,A24)-SUMIFS(Sell_History!$E:$E,Sell_History!$A:$A,A24,Sell_History!$B:$B,B24)))
F25: =IF(E25="","",MAX(0,E25-SUMIFS($E:$E,$D:$D,A25)-SUMIFS(Sell_History!$E:$E,Sell_History!$A:$A,A25,Sell_History!$B:$B,B25)))
F26: =IF(E26="","",MAX(0,E26-SUMIFS($E:$E,$D:$D,A26)-SUMIFS(Sell_History!$E:$E,Sell_History!$A:$A,A26,Sell_History!$B:$B,B26)))
F27: =IF(E27="","",MAX(0,E27-SUMIFS($E:$E,$D:$D,A27)-SUMIFS(Sell_History!$E:$E,Sell_History!$A:$A,A27,Sell_History!$B:$B,B27)))
F28: =IF(E28="","",MAX(0,E28-SUMIFS($E:$E,$D:$D,A28)-SUMIFS(Sell_History!$E:$E,Sell_History!$A:$A,A28,Sell_History!$B:$B,B28)))
F29: =IF(E29="","",MAX(0,E29-SUMIFS($E:$E,$D:$D,A29)-SUMIFS(Sell_History!$E:$E,Sell_History!$A:$A,A29,Sell_History!$B:$B,B29)))
F30: =IF(E30="","",MAX(0,E30-SUMIFS($E:$E,$D:$D,A30)-SUMIFS(Sell_History!$E:$E,Sell_History!$A:$A,A30,Sell_History!$B:$B,B30)))
F31: =IF(E31="","",MAX(0,E31-SUMIFS($E:$E,$D:$D,A31)-SUMIFS(Sell_History!$E:$E,Sell_History!$A:$A,A31,Sell_History!$B:$B,B31)))
F32: =IF(E32="","",MAX(0,E32-SUMIFS($E:$E,$D:$D,A32)-SUMIFS(Sell_History!$E:$E,Sell_History!$A:$A,A32,Sell_History!$B:$B,B32)))
F33: =IF(E33="","",MAX(0,E33-SUMIFS($E:$E,$D:$D,A33)-SUMIFS(Sell_History!$E:$E,Sell_History!$A:$A,A33,Sell_History!$B:$B,B33)))
F34: =IF(E34="","",MAX(0,E34-SUMIFS($E:$E,$D:$D,A34)-SUMIFS(Sell_History!$E:$E,Sell_History!$A:$A,A34,Sell_History!$B:$B,B34)))
... F200: =IF(E200="","",MAX(0,E200-SUMIFS($E:$E,$D:$D,A200)-SUMIFS(Sell_History!$E:$E,Sell_History!$A:$A,A200,Sell_History!$B:$B,B200)))

Sheet Order_History
A1: Listing ID | B1: CD ID | C1: Order ID | D1: Prev. Order ID | E1: Order Timestamp | F1: Sell Face Value ($) | G1: Asking Price ($)
A2: L-0001 | B2: TP03077 | C2: O-0001 | E2: 46254 | G2: 4656111.1
A3: L-0002 | B3: TP03085 | C3: O-0002 | E3: 46254 | G3: 3510101.1
A4: L-0003 | B4: TP03093 | C4: O-0003 | E4: 46254 | G4: 4613275.5
A5: L-0004 | B5: TP03104 | C5: O-0004 | E5: 46254 | G5: 3510101.1
A6: L-0005 | B6: TP00964 | C6: O-0005 | E6: 46249 | G6: 6673000
A7: L-0006 | B7: TP03429 | C7: O-0006 | E7: 46248 | G7: 20074367
A8: L-0007 | B8: TP00537 | C8: O-0007 | E8: 46248 | G8: 29702912
A9: L-0008 | B9: TP01034 | C9: O-0008 | E9: 46249 | G9: 30067117
A10: L-0009 | B10: TP00945 | C10: O-0009 | E10: 46253 | G10: 20087893
A11: L-0010 | B11: TP00558 | C11: O-0010 | E11: 46256 | G11: 50229268
A12: L-0015 | B12: TP01953 | C12: O-0011 | E12: 46257 | G12: 15961777
A13: L-0017 | B13: TP01961 | C13: O-0012 | E13: 46257 | G13: 5113209
... A16: L-0019 | B16: TP00575 | C16: O-0015 | E16: 46262 | G16: 45066545
A17: L-0019 | B17: TP00575 | C17: O-0016 | D17: O-0015 | E17: 46264 | G17: 45069570
A18: L-00191 | B18: TP00575 | C18: =IF(B18<>"","O-"&TEXT(ROW()-1,"0000"),"") -> O-0017 | E18: 46268 | F18: 22000000 | G18: 22012000
A19: L-00192 | B19: TP00575 | C19: =IF(B19<>"","O-"&TEXT(ROW()-1,"0000"),"") -> O-0018 | E19: 46270 | F19: 23000000 | G19: 23083000
A20: L-0020 | B20: TP00658 | C20: =IF(B20<>"","O-"&TEXT(ROW()-1,"0000"),"") -> O-0019 | E20: 46282 | G20: 19099703
A21: L-0021 | B21: TP00665 | C21: =IF(B21<>"","O-"&TEXT(ROW()-1,"0000"),"") -> O-0020 | E21: 46282 | G21: 14992240
A22: L-0022 | B22: TP60268 | C22: =IF(B22<>"","O-"&TEXT(ROW()-1,"0000"),"") -> O-0021 | E22: 46282 | G22: 9950000
A23: L-0030 | B23: TP22853 | C23: =IF(B23<>"","O-"&TEXT(ROW()-1,"0000"),"") -> O-0022 | E23: 46307 | G23: 50029515
A24: L-0030 | B24: TP22853 | C24: =IF(B24<>"","O-"&TEXT(ROW()-1,"0000"),"") -> O-0023 | D24: O-0022 | E24: 46308 | G24: 50037000
C25: =IF(B25<>"","O-"&TEXT(ROW()-1,"0000"),"")
C26: =IF(B26<>"","O-"&TEXT(ROW()-1,"0000"),"")
C27: =IF(B27<>"","O-"&TEXT(ROW()-1,"0000"),"")
C28: =IF(B28<>"","O-"&TEXT(ROW()-1,"0000"),"")
C29: =IF(B29<>"","O-"&TEXT(ROW()-1,"0000"),"")
C30: =IF(B30<>"","O-"&TEXT(ROW()-1,"0000"),"")
C31: =IF(B31<>"","O-"&TEXT(ROW()-1,"0000"),"")
C32: =IF(B32<>"","O-"&TEXT(ROW()-1,"0000"),"")
C33: =IF(B33<>"","O-"&TEXT(ROW()-1,"0000"),"")
C34: =IF(B34<>"","O-"&TEXT(ROW()-1,"0000"),"")
C35: =IF(B35<>"","O-"&TEXT(ROW()-1,"0000"),"")
C36: =IF(B36<>"","O-"&TEXT(ROW()-1,"0000"),"")
... C200: =IF(B200<>"","O-"&TEXT(ROW()-1,"0000"),"")

Sheet Sell_History
A1: Listing ID | B1: CD ID | C1: Order ID | D1: Matched Timestamp | E1: Sold Face Value ($)
A2: L-0001 | B2: TP03077 | C2: O-0001 | D2: 46255 | E2: =IF(OR(A2="",B2="",C2=""),"",IFERROR(LOOKUP(2,1/((Order_History!$A$2:$A$1000=A2)*(Order_History!$B$2:$B$1000=B2)*(Order_History!$C$2:$C$1000=C2)),Order_History!$F$2:$F$1000),"")) -> 0
A3: L-0002 | B3: TP03085 | C3: O-0002 | D3: 46255 | E3: =IF(OR(A3="",B3="",C3=""),"",IFERROR(LOOKUP(2,1/((Order_History!$A$2:$A$1000=A3)*(Order_History!$B$2:$B$1000=B3)*(Order_History!$C$2:$C$1000=C3)),Order_History!$F$2:$F$1000),"")) -> 0
A4: L-0003 | B4: TP03093 | C4: O-0003 | D4: 46255 | E4: =IF(OR(A4="",B4="",C4=""),"",IFERROR(LOOKUP(2,1/((Order_History!$A$2:$A$1000=A4)*(Order_History!$B$2:$B$1000=B4)*(Order_History!$C$2:$C$1000=C4)),Order_History!$F$2:$F$1000),"")) -> 0
A5: L-0004 | B5: TP03104 | C5: O-0004 | D5: 46255 | E5: =IF(OR(A5="",B5="",C5=""),"",IFERROR(LOOKUP(2,1/((Order_History!$A$2:$A$1000=A5)*(Order_History!$B$2:$B$1000=B5)*(Order_History!$C$2:$C$1000=C5)),Order_History!$F$2:$F$1000),"")) -> 0
A6: L-0005 | B6: TP00964 | C6: O-0005 | D6: 46249 | E6: =IF(OR(A6="",B6="",C6=""),"",IFERROR(LOOKUP(2,1/((Order_History!$A$2:$A$1000=A6)*(Order_History!$B$2:$B$1000=B6)*(Order_History!$C$2:$C$1000=C6)),Order_History!$F$2:$F$1000),"")) -> 0
A7: L-0006 | B7: TP03429 | C7: O-0006 | D7: 46248 | E7: =IF(OR(A7="",B7="",C7=""),"",IFERROR(LOOKUP(2,1/((Order_History!$A$2:$A$1000=A7)*(Order_History!$B$2:$B$1000=B7)*(Order_History!$C$2:$C$1000=C7)),Order_History!$F$2:$F$1000),"")) -> 0
A8: L-0007 | B8: TP00537 | C8: O-0007 | D8: 46248 | E8: =IF(OR(A8="",B8="",C8=""),"",IFERROR(LOOKUP(2,1/((Order_History!$A$2:$A$1000=A8)*(Order_History!$B$2:$B$1000=B8)*(Order_History!$C$2:$C$1000=C8)),Order_History!$F$2:$F$1000),"")) -> 0
A9: L-0008 | B9: TP01034 | C9: O-0008 | D9: 46249 | E9: =IF(OR(A9="",B9="",C9=""),"",IFERROR(LOOKUP(2,1/((Order_History!$A$2:$A$1000=A9)*(Order_History!$B$2:$B$1000=B9)*(Order_History!$C$2:$C$1000=C9)),Order_History!$F$2:$F$1000),"")) -> 0
A10: L-0009 | B10: TP00945 | C10: O-0009 | D10: 46253 | E10: =IF(OR(A10="",B10="",C10=""),"",IFERROR(LOOKUP(2,1/((Order_History!$A$2:$A$1000=A10)*(Order_History!$B$2:$B$1000=B10)*(Order_History!$C$2:$C$1000=C10)),Order_History!$F$2:$F$1000),"")) -> 0
A11: L-0010 | B11: TP00558 | C11: O-0010 | D11: 46257 | E11: =IF(OR(A11="",B11="",C11=""),"",IFERROR(LOOKUP(2,1/((Order_History!$A$2:$A$1000=A11)*(Order_History!$B$2:$B$1000=B11)*(Order_History!$C$2:$C$1000=C11)),Order_History!$F$2:$F$1000),"")) -> 0
A12: L-0015 | B12: TP01953 | C12: O-0011 | D12: 46258 | E12: =IF(OR(A12="",B12="",C12=""),"",IFERROR(LOOKUP(2,1/((Order_History!$A$2:$A$1000=A12)*(Order_History!$B$2:$B$1000=B12)*(Order_History!$C$2:$C$1000=C12)),Order_History!$F$2:$F$1000),"")) -> 0
A13: L-0017 | B13: TP01961 | C13: O-0012 | D13: 46258 | E13: =IF(OR(A13="",B13="",C13=""),"",IFERROR(LOOKUP(2,1/((Order_History!$A$2:$A$1000=A13)*(Order_History!$B$2:$B$1000=B13)*(Order_History!$C$2:$C$1000=C13)),Order_History!$F$2:$F$1000),"")) -> 0
... A20: L-0022 | B20: TP60268 | C20: O-0021 | D20: 46283 | E20: =IF(OR(A20="",B20="",C20=""),"",IFERROR(LOOKUP(2,1/((Order_History!$A$2:$A$1000=A20)*(Order_History!$B$2:$B$1000=B20)*(Order_History!$C$2:$C$1000=C20)),Order_History!$F$2:$F$1000),"")) -> 0
E21: =IF(OR(A21="",B21="",C21=""),"",IFERROR(LOOKUP(2,1/((Order_History!$A$2:$A$1000=A21)*(Order_History!$B$2:$B$1000=B21)*(Order_History!$C$2:$C$1000=C21)),Order_History!$F$2:$F$1000),""))
E22: =IF(OR(A22="",B22="",C22=""),"",IFERROR(LOOKUP(2,1/((Order_History!$A$2:$A$1000=A22)*(Order_History!$B$2:$B$1000=B22)*(Order_History!$C$2:$C$1000=C22)),Order_History!$F$2:$F$1000),""))
E23: =IF(OR(A23="",B23="",C23=""),"",IFERROR(LOOKUP(2,1/((Order_History!$A$2:$A$1000=A23)*(Order_History!$B$2:$B$1000=B23)*(Order_History!$C$2:$C$1000=C23)),Order_History!$F$2:$F$1000),""))
E24: =IF(OR(A24="",B24="",C24=""),"",IFERROR(LOOKUP(2,1/((Order_History!$A$2:$A$1000=A24)*(Order_History!$B$2:$B$1000=B24)*(Order_History!$C$2:$C$1000=C24)),Order_History!$F$2:$F$1000),""))
E25: =IF(C25="","",IFERROR(INDEX(Order_History!$F:$F,MATCH(C25,Order_History!$C:$C,0)),""))
E26: =IF(C26="","",IFERROR(INDEX(Order_History!$F:$F,MATCH(C26,Order_History!$C:$C,0)),""))
E27: =IF(C27="","",IFERROR(INDEX(Order_History!$F:$F,MATCH(C27,Order_History!$C:$C,0)),""))
E28: =IF(C28="","",IFERROR(INDEX(Order_History!$F:$F,MATCH(C28,Order_History!$C:$C,0)),""))
E29: =IF(C29="","",IFERROR(INDEX(Order_History!$F:$F,MATCH(C29,Order_History!$C:$C,0)),""))
E30: =IF(C30="","",IFERROR(INDEX(Order_History!$F:$F,MATCH(C30,Order_History!$C:$C,0)),""))
E31: =IF(C31="","",IFERROR(INDEX(Order_History!$F:$F,MATCH(C31,Order_History!$C:$C,0)),""))
E32: =IF(C32="","",IFERROR(INDEX(Order_History!$F:$F,MATCH(C32,Order_History!$C:$C,0)),""))
E33: =IF(C33="","",IFERROR(INDEX(Order_History!$F:$F,MATCH(C33,Order_History!$C:$C,0)),""))
E34: =IF(C34="","",IFERROR(INDEX(Order_History!$F:$F,MATCH(C34,Order_History!$C:$C,0)),""))
E35: =IF(C35="","",IFERROR(INDEX(Order_History!$F:$F,MATCH(C35,Order_History!$C:$C,0)),""))
E36: =IF(C36="","",IFERROR(INDEX(Order_History!$F:$F,MATCH(C36,Order_History!$C:$C,0)),""))
... E200: =IF(C200="","",IFERROR(INDEX(Order_History!$F:$F,MATCH(C200,Order_History!$C:$C,0)),""))

Sheet Trade_Results
A1: Listing ID | B1: CD ID | C1: Original Listing ID | D1: Buy Timestamp | E1: Sell Timestamp | F1: Sold Face Value ($) | G1: Original Face Value ($) | H1: Original Buy Price ($) | I1: Allocated Buy Cost ($) | J1: Sell Price ($) | K1: Liquidity Spread | L1: Gross Profit ($) | M1: Tax ($) | N1: Fee ($) | O1: Net Profit ($) | P1: ROI | Q1: Holding Period (Days) | R1: Effective Annual Return
A2: =IF(Sell_History!A2="","",Sell_History!A2) -> L-0001 | B2: =IF(Sell_History!B2="","",Sell_History!B2) -> TP03077 | C2: =IF(A2="","",IFERROR(IF(INDEX(Buy_History!$D:$D,MATCH(A2,Buy_History!$A:$A,0))="",A2,INDEX(Buy_History!$D:$D,MATCH(A2,Buy_History!$A:$A,0))),A2)) -> L-0001 | D2: =IF(C2="","",IFERROR(INDEX(Buy_History!$C:$C,MATCH(C2,Buy_History!$A:$A,0)),"")) -> 46253 | E2: =IF(A2="","",IFERROR(SUMIFS(Sell_History!$D:$D,Sell_History!$A:$A,A2,Sell_History!$B:$B,B2),"")) -> 46255 | F2: =IF(A2="","",IF(SUMIFS(Sell_History!$E:$E,Sell_History!$A:$A,A2,Sell_History!$B:$B,B2)=0,"",SUMIFS(Sell_History!$E:$E,Sell_History!$A:$A,A2,Sell_History!$B:$B,B2))) | G2: =IF(C2="","",IFERROR(INDEX(Buy_History!$E:$E,MATCH(C2,Buy_History!$A:$A,0)),"")) -> 0 | H2: =IF(C2="","",IFERROR(SUMIFS(Raw_Observations!$D:$D,Raw_Observations!$A:$A,C2,Raw_Observations!$B:$B,B2),"")) -> 4653638 | I2: =IF(H2="","",IF(OR(F2="",G2="",G2=0),H2,H2*F2/G2)) -> 4653638 | J2: =IFERROR(LOOKUP(2,1/((Order_History!$A$2:$A$200=A2)*(Order_History!$B$2:$B$200=B2)*(Order_History!$E$2:$E$200<=E2)),Order_History!$G$2:$G$200),"") -> 4656111.1 | K2: =IF(C2="","",IFERROR(SUMIFS(Pricing!$G:$G,Pricing!$A:$A,C2,Pricing!$B:$B,B2),"")) -> 0.02 | L2: =IF(OR(I2="",J2=""),"",J2-I2) -> 2473.1321 | M2: 0 | N2: 0 | O2: =IF(L2="","",L2-M2-N2) -> 2473.1321 | P2: =IF(OR(O2="",I2=""),"",O2/I2) -> 0.00053144059 | Q2: =IF(OR(D2="",E2=""),"",MAX(1,ROUNDUP(E2-D2,0))) -> 2 | R2: =IF(OR(P2="",Q2=""),"",(1+P2)^(365/Q2)-1) -> 0.10181866
A3: =IF(Sell_History!A3="","",Sell_History!A3) -> L-0002 | B3: =IF(Sell_History!B3="","",Sell_History!B3) -> TP03085 | C3: =IF(A3="","",IFERROR(IF(INDEX(Buy_History!$D:$D,MATCH(A3,Buy_History!$A:$A,0))="",A3,INDEX(Buy_History!$D:$D,MATCH(A3,Buy_History!$A:$A,0))),A3)) -> L-0002 | D3: =IF(C3="","",IFERROR(INDEX(Buy_History!$C:$C,MATCH(C3,Buy_History!$A:$A,0)),"")) -> 46253 | E3: =IF(A3="","",IFERROR(SUMIFS(Sell_History!$D:$D,Sell_History!$A:$A,A3,Sell_History!$B:$B,B3),"")) -> 46255 | F3: =IF(A3="","",IF(SUMIFS(Sell_History!$E:$E,Sell_History!$A:$A,A3,Sell_History!$B:$B,B3)=0,"",SUMIFS(Sell_History!$E:$E,Sell_History!$A:$A,A3,Sell_History!$B:$B,B3))) | G3: =IF(C3="","",IFERROR(INDEX(Buy_History!$E:$E,MATCH(C3,Buy_History!$A:$A,0)),"")) -> 0 | H3: =IF(C3="","",IFERROR(SUMIFS(Raw_Observations!$D:$D,Raw_Observations!$A:$A,C3,Raw_Observations!$B:$B,B3),"")) -> 3508365 | I3: =IF(H3="","",IF(OR(F3="",G3="",G3=0),H3,H3*F3/G3)) -> 3508365 | J3: =IFERROR(LOOKUP(2,1/((Order_History!$A$2:$A$200=A3)*(Order_History!$B$2:$B$200=B3)*(Order_History!$E$2:$E$200<=E3)),Order_History!$G$2:$G$200),"") -> 3510101.1 | K3: =IF(C3="","",IFERROR(SUMIFS(Pricing!$G:$G,Pricing!$A:$A,C3,Pricing!$B:$B,B3),"")) -> 0.02 | L3: =IF(OR(I3="",J3=""),"",J3-I3) -> 1736.0953 | M3: 0 | N3: 0 | O3: =IF(L3="","",L3-M3-N3) -> 1736.0953 | P3: =IF(OR(O3="",I3=""),"",O3/I3) -> 0.00049484454 | Q3: =IF(OR(D3="",E3=""),"",MAX(1,ROUNDUP(E3-D3,0))) -> 2 | R3: =IF(OR(P3="",Q3=""),"",(1+P3)^(365/Q3)-1) -> 0.094488128
A4: =IF(Sell_History!A4="","",Sell_History!A4) -> L-0003 | B4: =IF(Sell_History!B4="","",Sell_History!B4) -> TP03093 | C4: =IF(A4="","",IFERROR(IF(INDEX(Buy_History!$D:$D,MATCH(A4,Buy_History!$A:$A,0))="",A4,INDEX(Buy_History!$D:$D,MATCH(A4,Buy_History!$A:$A,0))),A4)) -> L-0003 | D4: =IF(C4="","",IFERROR(INDEX(Buy_History!$C:$C,MATCH(C4,Buy_History!$A:$A,0)),"")) -> 46253 | E4: =IF(A4="","",IFERROR(SUMIFS(Sell_History!$D:$D,Sell_History!$A:$A,A4,Sell_History!$B:$B,B4),"")) -> 46255 | F4: =IF(A4="","",IF(SUMIFS(Sell_History!$E:$E,Sell_History!$A:$A,A4,Sell_History!$B:$B,B4)=0,"",SUMIFS(Sell_History!$E:$E,Sell_History!$A:$A,A4,Sell_History!$B:$B,B4))) | G4: =IF(C4="","",IFERROR(INDEX(Buy_History!$E:$E,MATCH(C4,Buy_History!$A:$A,0)),"")) -> 0 | H4: =IF(C4="","",IFERROR(SUMIFS(Raw_Observations!$D:$D,Raw_Observations!$A:$A,C4,Raw_Observations!$B:$B,B4),"")) -> 4610986 | I4: =IF(H4="","",IF(OR(F4="",G4="",G4=0),H4,H4*F4/G4)) -> 4610986 | J4: =IFERROR(LOOKUP(2,1/((Order_History!$A$2:$A$200=A4)*(Order_History!$B$2:$B$200=B4)*(Order_History!$E$2:$E$200<=E4)),Order_History!$G$2:$G$200),"") -> 4613275.5 | K4: =IF(C4="","",IFERROR(SUMIFS(Pricing!$G:$G,Pricing!$A:$A,C4,Pricing!$B:$B,B4),"")) -> 0.02 | L4: =IF(OR(I4="",J4=""),"",J4-I4) -> 2289.5258 | M4: 0 | N4: 0 | O4: =IF(L4="","",L4-M4-N4) -> 2289.5258 | P4: =IF(OR(O4="",I4=""),"",O4/I4) -> 0.00049653713 | Q4: =IF(OR(D4="",E4=""),"",MAX(1,ROUNDUP(E4-D4,0))) -> 2 | R4: =IF(OR(P4="",Q4=""),"",(1+P4)^(365/Q4)-1) -> 0.094826099
A5: =IF(Sell_History!A5="","",Sell_History!A5) -> L-0004 | B5: =IF(Sell_History!B5="","",Sell_History!B5) -> TP03104 | C5: =IF(A5="","",IFERROR(IF(INDEX(Buy_History!$D:$D,MATCH(A5,Buy_History!$A:$A,0))="",A5,INDEX(Buy_History!$D:$D,MATCH(A5,Buy_History!$A:$A,0))),A5)) -> L-0004 | D5: =IF(C5="","",IFERROR(INDEX(Buy_History!$C:$C,MATCH(C5,Buy_History!$A:$A,0)),"")) -> 46253 | E5: =IF(A5="","",IFERROR(SUMIFS(Sell_History!$D:$D,Sell_History!$A:$A,A5,Sell_History!$B:$B,B5),"")) -> 46255 | F5: =IF(A5="","",IF(SUMIFS(Sell_History!$E:$E,Sell_History!$A:$A,A5,Sell_History!$B:$B,B5)=0,"",SUMIFS(Sell_History!$E:$E,Sell_History!$A:$A,A5,Sell_History!$B:$B,B5))) | G5: =IF(C5="","",IFERROR(INDEX(Buy_History!$E:$E,MATCH(C5,Buy_History!$A:$A,0)),"")) -> 0 | H5: =IF(C5="","",IFERROR(SUMIFS(Raw_Observations!$D:$D,Raw_Observations!$A:$A,C5,Raw_Observations!$B:$B,B5),"")) -> 3508456 | I5: =IF(H5="","",IF(OR(F5="",G5="",G5=0),H5,H5*F5/G5)) -> 3508456 | J5: =IFERROR(LOOKUP(2,1/((Order_History!$A$2:$A$200=A5)*(Order_History!$B$2:$B$200=B5)*(Order_History!$E$2:$E$200<=E5)),Order_History!$G$2:$G$200),"") -> 3510101.1 | K5: =IF(C5="","",IFERROR(SUMIFS(Pricing!$G:$G,Pricing!$A:$A,C5,Pricing!$B:$B,B5),"")) -> 0.02 | L5: =IF(OR(I5="",J5=""),"",J5-I5) -> 1645.0953 | M5: 0 | N5: 0 | O5: =IF(L5="","",L5-M5-N5) -> 1645.0953 | P5: =IF(OR(O5="",I5=""),"",O5/I5) -> 0.00046889437 | Q5: =IF(OR(D5="",E5=""),"",MAX(1,ROUNDUP(E5-D5,0))) -> 2 | R5: =IF(OR(P5="",Q5=""),"",(1+P5)^(365/Q5)-1) -> 0.089319475
A6: =IF(Sell_History!A6="","",Sell_History!A6) -> L-0005 | B6: =IF(Sell_History!B6="","",Sell_History!B6) -> TP00964 | C6: =IF(A6="","",IFERROR(IF(INDEX(Buy_History!$D:$D,MATCH(A6,Buy_History!$A:$A,0))="",A6,INDEX(Buy_History!$D:$D,MATCH(A6,Buy_History!$A:$A,0))),A6)) -> L-0005 | D6: =IF(C6="","",IFERROR(INDEX(Buy_History!$C:$C,MATCH(C6,Buy_History!$A:$A,0)),"")) -> 46245 | E6: =IF(A6="","",IFERROR(SUMIFS(Sell_History!$D:$D,Sell_History!$A:$A,A6,Sell_History!$B:$B,B6),"")) -> 46249 | F6: =IF(A6="","",IF(SUMIFS(Sell_History!$E:$E,Sell_History!$A:$A,A6,Sell_History!$B:$B,B6)=0,"",SUMIFS(Sell_History!$E:$E,Sell_History!$A:$A,A6,Sell_History!$B:$B,B6))) | G6: =IF(C6="","",IFERROR(INDEX(Buy_History!$E:$E,MATCH(C6,Buy_History!$A:$A,0)),"")) -> 0 | H6: =IF(C6="","",IFERROR(SUMIFS(Raw_Observations!$D:$D,Raw_Observations!$A:$A,C6,Raw_Observations!$B:$B,B6),"")) -> 6671860 | I6: =IF(H6="","",IF(OR(F6="",G6="",G6=0),H6,H6*F6/G6)) -> 6671860 | J6: =IFERROR(LOOKUP(2,1/((Order_History!$A$2:$A$200=A6)*(Order_History!$B$2:$B$200=B6)*(Order_History!$E$2:$E$200<=E6)),Order_History!$G$2:$G$200),"") -> 6673000 | K6: =IF(C6="","",IFERROR(SUMIFS(Pricing!$G:$G,Pricing!$A:$A,C6,Pricing!$B:$B,B6),"")) -> 0.002 | L6: =IF(OR(I6="",J6=""),"",J6-I6) -> 1140 | M6: 0 | N6: 0 | O6: =IF(L6="","",L6-M6-N6) -> 1140 | P6: =IF(OR(O6="",I6=""),"",O6/I6) -> 0.00017086689 | Q6: =IF(OR(D6="",E6=""),"",MAX(1,ROUNDUP(E6-D6,0))) -> 4 | R6: =IF(OR(P6="",Q6=""),"",(1+P6)^(365/Q6)-1) -> 0.015712435
A7: =IF(Sell_History!A7="","",Sell_History!A7) -> L-0006 | B7: =IF(Sell_History!B7="","",Sell_History!B7) -> TP03429 | C7: =IF(A7="","",IFERROR(IF(INDEX(Buy_History!$D:$D,MATCH(A7,Buy_History!$A:$A,0))="",A7,INDEX(Buy_History!$D:$D,MATCH(A7,Buy_History!$A:$A,0))),A7)) -> L-0006 | D7: =IF(C7="","",IFERROR(INDEX(Buy_History!$C:$C,MATCH(C7,Buy_History!$A:$A,0)),"")) -> 46247 | E7: =IF(A7="","",IFERROR(SUMIFS(Sell_History!$D:$D,Sell_History!$A:$A,A7,Sell_History!$B:$B,B7),"")) -> 46248 | F7: =IF(A7="","",IF(SUMIFS(Sell_History!$E:$E,Sell_History!$A:$A,A7,Sell_History!$B:$B,B7)=0,"",SUMIFS(Sell_History!$E:$E,Sell_History!$A:$A,A7,Sell_History!$B:$B,B7))) | G7: =IF(C7="","",IFERROR(INDEX(Buy_History!$E:$E,MATCH(C7,Buy_History!$A:$A,0)),"")) -> 0 | H7: =IF(C7="","",IFERROR(SUMIFS(Raw_Observations!$D:$D,Raw_Observations!$A:$A,C7,Raw_Observations!$B:$B,B7),"")) -> 20060000 | I7: =IF(H7="","",IF(OR(F7="",G7="",G7=0),H7,H7*F7/G7)) -> 20060000 | J7: =IFERROR(LOOKUP(2,1/((Order_History!$A$2:$A$200=A7)*(Order_History!$B$2:$B$200=B7)*(Order_History!$E$2:$E$200<=E7)),Order_History!$G$2:$G$200),"") -> 20074367 | K7: =IF(C7="","",IFERROR(SUMIFS(Pricing!$G:$G,Pricing!$A:$A,C7,Pricing!$B:$B,B7),"")) -> 0.003 | L7: =IF(OR(I7="",J7=""),"",J7-I7) -> 14367 | M7: 0 | N7: 0 | O7: =IF(L7="","",L7-M7-N7) -> 14367 | P7: =IF(OR(O7="",I7=""),"",O7/I7) -> 0.0007162014 | Q7: =IF(OR(D7="",E7=""),"",MAX(1,ROUNDUP(E7-D7,0))) -> 1 | R7: =IF(OR(P7="",Q7=""),"",(1+P7)^(365/Q7)-1) -> 0.29864309
A8: =IF(Sell_History!A8="","",Sell_History!A8) -> L-0007 | B8: =IF(Sell_History!B8="","",Sell_History!B8) -> TP00537 | C8: =IF(A8="","",IFERROR(IF(INDEX(Buy_History!$D:$D,MATCH(A8,Buy_History!$A:$A,0))="",A8,INDEX(Buy_History!$D:$D,MATCH(A8,Buy_History!$A:$A,0))),A8)) -> L-0007 | D8: =IF(C8="","",IFERROR(INDEX(Buy_History!$C:$C,MATCH(C8,Buy_History!$A:$A,0)),"")) -> 46248 | E8: =IF(A8="","",IFERROR(SUMIFS(Sell_History!$D:$D,Sell_History!$A:$A,A8,Sell_History!$B:$B,B8),"")) -> 46248 | F8: =IF(A8="","",IF(SUMIFS(Sell_History!$E:$E,Sell_History!$A:$A,A8,Sell_History!$B:$B,B8)=0,"",SUMIFS(Sell_History!$E:$E,Sell_History!$A:$A,A8,Sell_History!$B:$B,B8))) | G8: =IF(C8="","",IFERROR(INDEX(Buy_History!$E:$E,MATCH(C8,Buy_History!$A:$A,0)),"")) -> 0 | H8: =IF(C8="","",IFERROR(SUMIFS(Raw_Observations!$D:$D,Raw_Observations!$A:$A,C8,Raw_Observations!$B:$B,B8),"")) -> 29685213 | I8: =IF(H8="","",IF(OR(F8="",G8="",G8=0),H8,H8*F8/G8)) -> 29685213 | J8: =IFERROR(LOOKUP(2,1/((Order_History!$A$2:$A$200=A8)*(Order_History!$B$2:$B$200=B8)*(Order_History!$E$2:$E$200<=E8)),Order_History!$G$2:$G$200),"") -> 29702912 | K8: =IF(C8="","",IFERROR(SUMIFS(Pricing!$G:$G,Pricing!$A:$A,C8,Pricing!$B:$B,B8),"")) -> 0.0034 | L8: =IF(OR(I8="",J8=""),"",J8-I8) -> 17699 | M8: 0 | N8: 0 | O8: =IF(L8="","",L8-M8-N8) -> 17699 | P8: =IF(OR(O8="",I8=""),"",O8/I8) -> 0.00059622277 | Q8: =IF(OR(D8="",E8=""),"",MAX(1,ROUNDUP(E8-D8,0))) -> 1 | R8: =IF(OR(P8="",Q8=""),"",(1+P8)^(365/Q8)-1) -> 0.24303561
A9: =IF(Sell_History!A9="","",Sell_History!A9) -> L-0008 | B9: =IF(Sell_History!B9="","",Sell_History!B9) -> TP01034 | C9: =IF(A9="","",IFERROR(IF(INDEX(Buy_History!$D:$D,MATCH(A9,Buy_History!$A:$A,0))="",A9,INDEX(Buy_History!$D:$D,MATCH(A9,Buy_History!$A:$A,0))),A9)) -> L-0008 | D9: =IF(C9="","",IFERROR(INDEX(Buy_History!$C:$C,MATCH(C9,Buy_History!$A:$A,0)),"")) -> 46248 | E9: =IF(A9="","",IFERROR(SUMIFS(Sell_History!$D:$D,Sell_History!$A:$A,A9,Sell_History!$B:$B,B9),"")) -> 46249 | F9: =IF(A9="","",IF(SUMIFS(Sell_History!$E:$E,Sell_History!$A:$A,A9,Sell_History!$B:$B,B9)=0,"",SUMIFS(Sell_History!$E:$E,Sell_History!$A:$A,A9,Sell_History!$B:$B,B9))) | G9: =IF(C9="","",IFERROR(INDEX(Buy_History!$E:$E,MATCH(C9,Buy_History!$A:$A,0)),"")) -> 0 | H9: =IF(C9="","",IFERROR(SUMIFS(Raw_Observations!$D:$D,Raw_Observations!$A:$A,C9,Raw_Observations!$B:$B,B9),"")) -> 30046000 | I9: =IF(H9="","",IF(OR(F9="",G9="",G9=0),H9,H9*F9/G9)) -> 30046000 | J9: =IFERROR(LOOKUP(2,1/((Order_History!$A$2:$A$200=A9)*(Order_History!$B$2:$B$200=B9)*(Order_History!$E$2:$E$200<=E9)),Order_History!$G$2:$G$200),"") -> 30067117 | K9: =IF(C9="","",IFERROR(SUMIFS(Pricing!$G:$G,Pricing!$A:$A,C9,Pricing!$B:$B,B9),"")) -> 0.003 | L9: =IF(OR(I9="",J9=""),"",J9-I9) -> 21117 | M9: 0 | N9: 0 | O9: =IF(L9="","",L9-M9-N9) -> 21117 | P9: =IF(OR(O9="",I9=""),"",O9/I9) -> 0.00070282234 | Q9: =IF(OR(D9="",E9=""),"",MAX(1,ROUNDUP(E9-D9,0))) -> 1 | R9: =IF(OR(P9="",Q9=""),"",(1+P9)^(365/Q9)-1) -> 0.29232129
A10: =IF(Sell_History!A10="","",Sell_History!A10) -> L-0009 | B10: =IF(Sell_History!B10="","",Sell_History!B10) -> TP00945 | C10: =IF(A10="","",IFERROR(IF(INDEX(Buy_History!$D:$D,MATCH(A10,Buy_History!$A:$A,0))="",A10,INDEX(Buy_History!$D:$D,MATCH(A10,Buy_History!$A:$A,0))),A10)) -> L-0009 | D10: =IF(C10="","",IFERROR(INDEX(Buy_History!$C:$C,MATCH(C10,Buy_History!$A:$A,0)),"")) -> 46251 | E10: =IF(A10="","",IFERROR(SUMIFS(Sell_History!$D:$D,Sell_History!$A:$A,A10,Sell_History!$B:$B,B10),"")) -> 46253 | F10: =IF(A10="","",IF(SUMIFS(Sell_History!$E:$E,Sell_History!$A:$A,A10,Sell_History!$B:$B,B10)=0,"",SUMIFS(Sell_History!$E:$E,Sell_History!$A:$A,A10,Sell_History!$B:$B,B10))) | G10: =IF(C10="","",IFERROR(INDEX(Buy_History!$E:$E,MATCH(C10,Buy_History!$A:$A,0)),"")) -> 0 | H10: =IF(C10="","",IFERROR(SUMIFS(Raw_Observations!$D:$D,Raw_Observations!$A:$A,C10,Raw_Observations!$B:$B,B10),"")) -> 20064000 | I10: =IF(H10="","",IF(OR(F10="",G10="",G10=0),H10,H10*F10/G10)) -> 20064000 | J10: =IFERROR(LOOKUP(2,1/((Order_History!$A$2:$A$200=A10)*(Order_History!$B$2:$B$200=B10)*(Order_History!$E$2:$E$200<=E10)),Order_History!$G$2:$G$200),"") -> 20087893 | K10: =IF(C10="","",IFERROR(SUMIFS(Pricing!$G:$G,Pricing!$A:$A,C10,Pricing!$B:$B,B10),"")) -> 0.01 | L10: =IF(OR(I10="",J10=""),"",J10-I10) -> 23893 | M10: 0 | N10: 0 | O10: =IF(L10="","",L10-M10-N10) -> 23893 | P10: =IF(OR(O10="",I10=""),"",O10/I10) -> 0.0011908393 | Q10: =IF(OR(D10="",E10=""),"",MAX(1,ROUNDUP(E10-D10,0))) -> 2 | R10: =IF(OR(P10="",Q10=""),"",(1+P10)^(365/Q10)-1) -> 0.2425912
A11: =IF(Sell_History!A11="","",Sell_History!A11) -> L-0010 | B11: =IF(Sell_History!B11="","",Sell_History!B11) -> TP00558 | C11: =IF(A11="","",IFERROR(IF(INDEX(Buy_History!$D:$D,MATCH(A11,Buy_History!$A:$A,0))="",A11,INDEX(Buy_History!$D:$D,MATCH(A11,Buy_History!$A:$A,0))),A11)) -> L-0010 | D11: =IF(C11="","",IFERROR(INDEX(Buy_History!$C:$C,MATCH(C11,Buy_History!$A:$A,0)),"")) -> 46256 | E11: =IF(A11="","",IFERROR(SUMIFS(Sell_History!$D:$D,Sell_History!$A:$A,A11,Sell_History!$B:$B,B11),"")) -> 46257 | F11: =IF(A11="","",IF(SUMIFS(Sell_History!$E:$E,Sell_History!$A:$A,A11,Sell_History!$B:$B,B11)=0,"",SUMIFS(Sell_History!$E:$E,Sell_History!$A:$A,A11,Sell_History!$B:$B,B11))) | G11: =IF(C11="","",IFERROR(INDEX(Buy_History!$E:$E,MATCH(C11,Buy_History!$A:$A,0)),"")) -> 0 | H11: =IF(C11="","",IFERROR(SUMIFS(Raw_Observations!$D:$D,Raw_Observations!$A:$A,C11,Raw_Observations!$B:$B,B11),"")) -> 50217550 | I11: =IF(H11="","",IF(OR(F11="",G11="",G11=0),H11,H11*F11/G11)) -> 50217550 | J11: =IFERROR(LOOKUP(2,1/((Order_History!$A$2:$A$200=A11)*(Order_History!$B$2:$B$200=B11)*(Order_History!$E$2:$E$200<=E11)),Order_History!$G$2:$G$200),"") -> 50229268 | K11: =IF(C11="","",IFERROR(SUMIFS(Pricing!$G:$G,Pricing!$A:$A,C11,Pricing!$B:$B,B11),"")) -> 0.017 | L11: =IF(OR(I11="",J11=""),"",J11-I11) -> 11717.883 | M11: 0 | N11: 0 | O11: =IF(L11="","",L11-M11-N11) -> 11717.883 | P11: =IF(OR(O11="",I11=""),"",O11/I11) -> 0.00023334239 | Q11: =IF(OR(D11="",E11=""),"",MAX(1,ROUNDUP(E11-D11,0))) -> 1 | R11: =IF(OR(P11="",Q11=""),"",(1+P11)^(365/Q11)-1) -> 0.088891316
A12: =IF(Sell_History!A12="","",Sell_History!A12) -> L-0015 | B12: =IF(Sell_History!B12="","",Sell_History!B12) -> TP01953 | C12: =IF(A12="","",IFERROR(IF(INDEX(Buy_History!$D:$D,MATCH(A12,Buy_History!$A:$A,0))="",A12,INDEX(Buy_History!$D:$D,MATCH(A12,Buy_History!$A:$A,0))),A12)) -> L-0015 | D12: =IF(C12="","",IFERROR(INDEX(Buy_History!$C:$C,MATCH(C12,Buy_History!$A:$A,0)),"")) -> 46257 | E12: =IF(A12="","",IFERROR(SUMIFS(Sell_History!$D:$D,Sell_History!$A:$A,A12,Sell_History!$B:$B,B12),"")) -> 46258 | F12: =IF(A12="","",IF(SUMIFS(Sell_History!$E:$E,Sell_History!$A:$A,A12,Sell_History!$B:$B,B12)=0,"",SUMIFS(Sell_History!$E:$E,Sell_History!$A:$A,A12,Sell_History!$B:$B,B12))) | G12: =IF(C12="","",IFERROR(INDEX(Buy_History!$E:$E,MATCH(C12,Buy_History!$A:$A,0)),"")) -> 0 | H12: =IF(C12="","",IFERROR(SUMIFS(Raw_Observations!$D:$D,Raw_Observations!$A:$A,C12,Raw_Observations!$B:$B,B12),"")) -> 15950000 | I12: =IF(H12="","",IF(OR(F12="",G12="",G12=0),H12,H12*F12/G12)) -> 15950000 | J12: =IFERROR(LOOKUP(2,1/((Order_History!$A$2:$A$200=A12)*(Order_History!$B$2:$B$200=B12)*(Order_History!$E$2:$E$200<=E12)),Order_History!$G$2:$G$200),"") -> 15961777 | K12: =IF(C12="","",IFERROR(SUMIFS(Pricing!$G:$G,Pricing!$A:$A,C12,Pricing!$B:$B,B12),"")) -> 0.01 | L12: =IF(OR(I12="",J12=""),"",J12-I12) -> 11777 | M12: 0 | N12: 0 | O12: =IF(L12="","",L12-M12-N12) -> 11777 | P12: =IF(OR(O12="",I12=""),"",O12/I12) -> 0.00073836991 | Q12: =IF(OR(D12="",E12=""),"",MAX(1,ROUNDUP(E12-D12,0))) -> 1 | R12: =IF(OR(P12="",Q12=""),"",(1+P12)^(365/Q12)-1) -> 0.309186
A13: =IF(Sell_History!A13="","",Sell_History!A13) -> L-0017 | B13: =IF(Sell_History!B13="","",Sell_History!B13) -> TP01961 | C13: =IF(A13="","",IFERROR(IF(INDEX(Buy_History!$D:$D,MATCH(A13,Buy_History!$A:$A,0))="",A13,INDEX(Buy_History!$D:$D,MATCH(A13,Buy_History!$A:$A,0))),A13)) -> L-0017 | D13: =IF(C13="","",IFERROR(INDEX(Buy_History!$C:$C,MATCH(C13,Buy_History!$A:$A,0)),"")) -> 46257 | E13: =IF(A13="","",IFERROR(SUMIFS(Sell_History!$D:$D,Sell_History!$A:$A,A13,Sell_History!$B:$B,B13),"")) -> 46258 | F13: =IF(A13="","",IF(SUMIFS(Sell_History!$E:$E,Sell_History!$A:$A,A13,Sell_History!$B:$B,B13)=0,"",SUMIFS(Sell_History!$E:$E,Sell_History!$A:$A,A13,Sell_History!$B:$B,B13))) | G13: =IF(C13="","",IFERROR(INDEX(Buy_History!$E:$E,MATCH(C13,Buy_History!$A:$A,0)),"")) -> 0 | H13: =IF(C13="","",IFERROR(SUMIFS(Raw_Observations!$D:$D,Raw_Observations!$A:$A,C13,Raw_Observations!$B:$B,B13),"")) -> 5111466 | I13: =IF(H13="","",IF(OR(F13="",G13="",G13=0),H13,H13*F13/G13)) -> 5111466 | J13: =IFERROR(LOOKUP(2,1/((Order_History!$A$2:$A$200=A13)*(Order_History!$B$2:$B$200=B13)*(Order_History!$E$2:$E$200<=E13)),Order_History!$G$2:$G$200),"") -> 5113209 | K13: =IF(C13="","",IFERROR(SUMIFS(Pricing!$G:$G,Pricing!$A:$A,C13,Pricing!$B:$B,B13),"")) -> 0.012 | L13: =IF(OR(I13="",J13=""),"",J13-I13) -> 1743 | M13: 0 | N13: 0 | O13: =IF(L13="","",L13-M13-N13) -> 1743 | P13: =IF(OR(O13="",I13=""),"",O13/I13) -> 0.00034099806 | Q13: =IF(OR(D13="",E13=""),"",MAX(1,ROUNDUP(E13-D13,0))) -> 1 | R13: =IF(OR(P13="",Q13=""),"",(1+P13)^(365/Q13)-1) -> 0.13251755
... A17: =IF(Sell_History!A17="","",Sell_History!A17) -> L-00192 | B17: =IF(Sell_History!B17="","",Sell_History!B17) -> TP00575 | C17: =IF(A17="","",IFERROR(IF(INDEX(Buy_History!$D:$D,MATCH(A17,Buy_History!$A:$A,0))="",A17,INDEX(Buy_History!$D:$D,MATCH(A17,Buy_History!$A:$A,0))),A17)) -> L-0019 | D17: =IF(C17="","",IFERROR(INDEX(Buy_History!$C:$C,MATCH(C17,Buy_History!$A:$A,0)),"")) -> 46262 | E17: =IF(A17="","",IFERROR(SUMIFS(Sell_History!$D:$D,Sell_History!$A:$A,A17,Sell_History!$B:$B,B17),"")) -> 46271 | F17: =IF(A17="","",IF(SUMIFS(Sell_History!$E:$E,Sell_History!$A:$A,A17,Sell_History!$B:$B,B17)=0,"",SUMIFS(Sell_History!$E:$E,Sell_History!$A:$A,A17,Sell_History!$B:$B,B17))) -> 23000000 | G17: =IF(C17="","",IFERROR(INDEX(Buy_History!$E:$E,MATCH(C17,Buy_History!$A:$A,0)),"")) -> 45000000 | H17: =IF(C17="","",IFERROR(SUMIFS(Raw_Observations!$D:$D,Raw_Observations!$A:$A,C17,Raw_Observations!$B:$B,B17),"")) -> 45016027 | I17: =IF(H17="","",IF(OR(F17="",G17="",G17=0),H17,H17*F17/G17)) -> 23008192 | J17: =IFERROR(LOOKUP(2,1/((Order_History!$A$2:$A$200=A17)*(Order_History!$B$2:$B$200=B17)*(Order_History!$E$2:$E$200<=E17)),Order_History!$G$2:$G$200),"") -> 23083000 | K17: =IF(C17="","",IFERROR(SUMIFS(Pricing!$G:$G,Pricing!$A:$A,C17,Pricing!$B:$B,B17),"")) -> 0.015 | L17: =IF(OR(I17="",J17=""),"",J17-I17) -> 74808.422 | M17: 0 | N17: 0 | O17: =IF(L17="","",L17-M17-N17) -> 74808.422 | P17: =IF(OR(O17="",I17=""),"",O17/I17) -> 0.0032513821 | Q17: =IF(OR(D17="",E17=""),"",MAX(1,ROUNDUP(E17-D17,0))) -> 9 | R17: =IF(OR(P17="",Q17=""),"",(1+P17)^(365/Q17)-1) -> 0.14070638
A18: =IF(Sell_History!A18="","",Sell_History!A18) -> L-0020 | B18: =IF(Sell_History!B18="","",Sell_History!B18) -> TP00658 | C18: =IF(A18="","",IFERROR(INDEX(Buy_History!#REF!,MATCH(A18,Buy_History!$A:$A,0)),A18)) -> L-0020 | D18: =IF(C18="","",IFERROR(INDEX(Buy_History!$C:$C,MATCH(C18,Buy_History!$A:$A,0)),"")) -> 46280 | E18: =IF(A18="","",IFERROR(SUMIFS(Sell_History!$D:$D,Sell_History!$A:$A,A18,Sell_History!$B:$B,B18),"")) -> 46284 | F18: =IF(A18="","",IF(SUMIFS(Sell_History!$E:$E,Sell_History!$A:$A,A18,Sell_History!$B:$B,B18)=0,"",SUMIFS(Sell_History!$E:$E,Sell_History!$A:$A,A18,Sell_History!$B:$B,B18))) | G18: =IF(C18="","",IFERROR(INDEX(Buy_History!$E:$E,MATCH(C18,Buy_History!$A:$A,0)),"")) -> 0 | H18: =IF(C18="","",IFERROR(SUMIFS(Raw_Observations!$D:$D,Raw_Observations!$A:$A,C18,Raw_Observations!$B:$B,B18),"")) -> 19091800 | I18: =IF(H18="","",IF(OR(F18="",G18="",G18=0),H18,H18*F18/G18)) -> 19091800 | J18: =IFERROR(LOOKUP(2,1/((Order_History!$A$2:$A$200=A18)*(Order_History!$B$2:$B$200=B18)*(Order_History!$E$2:$E$200<=E18)),Order_History!$G$2:$G$200),"") -> 19099703 | K18: =IF(C18="","",IFERROR(SUMIFS(Pricing!$G:$G,Pricing!$A:$A,C18,Pricing!$B:$B,B18),"")) -> 0.0295 | L18: =IF(OR(I18="",J18=""),"",J18-I18) -> 7903.1851 | M18: 0 | N18: 0 | O18: =IF(L18="","",L18-M18-N18) -> 7903.1851 | P18: =IF(OR(O18="",I18=""),"",O18/I18) -> 0.00041395705 | Q18: =IF(OR(D18="",E18=""),"",MAX(1,ROUNDUP(E18-D18,0))) -> 4 | R18: =IF(OR(P18="",Q18=""),"",(1+P18)^(365/Q18)-1) -> 0.038487953
A19: =IF(Sell_History!A19="","",Sell_History!A19) -> L-0021 | B19: =IF(Sell_History!B19="","",Sell_History!B19) -> TP00665 | C19: =IF(A19="","",IFERROR(INDEX(Buy_History!#REF!,MATCH(A19,Buy_History!$A:$A,0)),A19)) -> L-0021 | D19: =IF(C19="","",IFERROR(INDEX(Buy_History!$C:$C,MATCH(C19,Buy_History!$A:$A,0)),"")) -> 46280 | E19: =IF(A19="","",IFERROR(SUMIFS(Sell_History!$D:$D,Sell_History!$A:$A,A19,Sell_History!$B:$B,B19),"")) -> 46284 | F19: =IF(A19="","",IF(SUMIFS(Sell_History!$E:$E,Sell_History!$A:$A,A19,Sell_History!$B:$B,B19)=0,"",SUMIFS(Sell_History!$E:$E,Sell_History!$A:$A,A19,Sell_History!$B:$B,B19))) | G19: =IF(C19="","",IFERROR(INDEX(Buy_History!$E:$E,MATCH(C19,Buy_History!$A:$A,0)),"")) -> 0 | H19: =IF(C19="","",IFERROR(SUMIFS(Raw_Observations!$D:$D,Raw_Observations!$A:$A,C19,Raw_Observations!$B:$B,B19),"")) -> 14986000 | I19: =IF(H19="","",IF(OR(F19="",G19="",G19=0),H19,H19*F19/G19)) -> 14986000 | J19: =IFERROR(LOOKUP(2,1/((Order_History!$A$2:$A$200=A19)*(Order_History!$B$2:$B$200=B19)*(Order_History!$E$2:$E$200<=E19)),Order_History!$G$2:$G$200),"") -> 14992240 | K19: =IF(C19="","",IFERROR(SUMIFS(Pricing!$G:$G,Pricing!$A:$A,C19,Pricing!$B:$B,B19),"")) -> 0.0295 | L19: =IF(OR(I19="",J19=""),"",J19-I19) -> 6239.9308 | M19: 0 | N19: 0 | O19: =IF(L19="","",L19-M19-N19) -> 6239.9308 | P19: =IF(OR(O19="",I19=""),"",O19/I19) -> 0.00041638401 | Q19: =IF(OR(D19="",E19=""),"",MAX(1,ROUNDUP(E19-D19,0))) -> 4 | R19: =IF(OR(P19="",Q19=""),"",(1+P19)^(365/Q19)-1) -> 0.038717868
A20: =IF(Sell_History!A20="","",Sell_History!A20) -> L-0022 | B20: =IF(Sell_History!B20="","",Sell_History!B20) -> TP60268 | C20: =IF(A20="","",IFERROR(INDEX(Buy_History!#REF!,MATCH(A20,Buy_History!$A:$A,0)),A20)) -> L-0022 | D20: =IF(C20="","",IFERROR(INDEX(Buy_History!$C:$C,MATCH(C20,Buy_History!$A:$A,0)),"")) -> 46282 | E20: =IF(A20="","",IFERROR(SUMIFS(Sell_History!$D:$D,Sell_History!$A:$A,A20,Sell_History!$B:$B,B20),"")) -> 46283 | F20: =IF(A20="","",IF(SUMIFS(Sell_History!$E:$E,Sell_History!$A:$A,A20,Sell_History!$B:$B,B20)=0,"",SUMIFS(Sell_History!$E:$E,Sell_History!$A:$A,A20,Sell_History!$B:$B,B20))) | G20: =IF(C20="","",IFERROR(INDEX(Buy_History!$E:$E,MATCH(C20,Buy_History!$A:$A,0)),"")) -> 0 | H20: =IF(C20="","",IFERROR(SUMIFS(Raw_Observations!$D:$D,Raw_Observations!$A:$A,C20,Raw_Observations!$B:$B,B20),"")) -> 9945000 | I20: =IF(H20="","",IF(OR(F20="",G20="",G20=0),H20,H20*F20/G20)) -> 9945000 | J20: =IFERROR(LOOKUP(2,1/((Order_History!$A$2:$A$200=A20)*(Order_History!$B$2:$B$200=B20)*(Order_History!$E$2:$E$200<=E20)),Order_History!$G$2:$G$200),"") -> 9950000 | K20: =IF(C20="","",IFERROR(SUMIFS(Pricing!$G:$G,Pricing!$A:$A,C20,Pricing!$B:$B,B20),"")) -> 0 | L20: =IF(OR(I20="",J20=""),"",J20-I20) -> 5000 | M20: 0 | N20: 0 | O20: =IF(L20="","",L20-M20-N20) -> 5000 | P20: =IF(OR(O20="",I20=""),"",O20/I20) -> 0.00050276521 | Q20: =IF(OR(D20="",E20=""),"",MAX(1,ROUNDUP(E20-D20,0))) -> 1 | R20: =IF(OR(P20="",Q20=""),"",(1+P20)^(365/Q20)-1) -> 0.20137074
A21: =IF(Sell_History!A21="","",Sell_History!A21) | B21: =IF(Sell_History!B21="","",Sell_History!B21) | C21: =IF(A21="","",IFERROR(INDEX(Buy_History!#REF!,MATCH(A21,Buy_History!$A:$A,0)),A21)) | D21: =IF(C21="","",IFERROR(INDEX(Buy_History!$C:$C,MATCH(C21,Buy_History!$A:$A,0)),"")) | E21: =IF(A21="","",IFERROR(SUMIFS(Sell_History!$D:$D,Sell_History!$A:$A,A21,Sell_History!$B:$B,B21),"")) | F21: =IF(A21="","",IF(SUMIFS(Sell_History!$E:$E,Sell_History!$A:$A,A21,Sell_History!$B:$B,B21)=0,"",SUMIFS(Sell_History!$E:$E,Sell_History!$A:$A,A21,Sell_History!$B:$B,B21))) | G21: =IF(C21="","",IFERROR(INDEX(Buy_History!$E:$E,MATCH(C21,Buy_History!$A:$A,0)),"")) | H21: =IF(C21="","",IFERROR(SUMIFS(Raw_Observations!$D:$D,Raw_Observations!$A:$A,C21,Raw_Observations!$B:$B,B21),"")) | I21: =IF(H21="","",IF(OR(F21="",G21="",G21=0),H21,H21*F21/G21)) | J21: =IFERROR(LOOKUP(2,1/((Order_History!$A$2:$A$200=A21)*(Order_History!$B$2:$B$200=B21)*(Order_History!$E$2:$E$200<=E21)),Order_History!$G$2:$G$200),"") -> 0 | K21: =IF(C21="","",IFERROR(SUMIFS(Pricing!$G:$G,Pricing!$A:$A,C21,Pricing!$B:$B,B21),"")) | L21: =IF(OR(I21="",J21=""),"",J21-I21) | M21: 0 | N21: 0 | O21: =IF(L21="","",L21-M21-N21) | P21: =IF(OR(O21="",I21=""),"",O21/I21) | Q21: =IF(OR(D21="",E21=""),"",MAX(1,ROUNDUP(E21-D21,0))) | R21: =IF(OR(P21="",Q21=""),"",(1+P21)^(365/Q21)-1)
A22: =IF(Sell_History!A22="","",Sell_History!A22) | B22: =IF(Sell_History!B22="","",Sell_History!B22) | C22: =IF(A22="","",IFERROR(INDEX(Buy_History!#REF!,MATCH(A22,Buy_History!$A:$A,0)),A22)) | D22: =IF(C22="","",IFERROR(INDEX(Buy_History!$C:$C,MATCH(C22,Buy_History!$A:$A,0)),"")) | E22: =IF(A22="","",IFERROR(SUMIFS(Sell_History!$D:$D,Sell_History!$A:$A,A22,Sell_History!$B:$B,B22),"")) | F22: =IF(A22="","",IF(SUMIFS(Sell_History!$E:$E,Sell_History!$A:$A,A22,Sell_History!$B:$B,B22)=0,"",SUMIFS(Sell_History!$E:$E,Sell_History!$A:$A,A22,Sell_History!$B:$B,B22))) | G22: =IF(C22="","",IFERROR(INDEX(Buy_History!$E:$E,MATCH(C22,Buy_History!$A:$A,0)),"")) | H22: =IF(C22="","",IFERROR(SUMIFS(Raw_Observations!$D:$D,Raw_Observations!$A:$A,C22,Raw_Observations!$B:$B,B22),"")) | I22: =IF(H22="","",IF(OR(F22="",G22="",G22=0),H22,H22*F22/G22)) | J22: =IFERROR(LOOKUP(2,1/((Order_History!$A$2:$A$200=A22)*(Order_History!$B$2:$B$200=B22)*(Order_History!$E$2:$E$200<=E22)),Order_History!$G$2:$G$200),"") -> 0 | K22: =IF(C22="","",IFERROR(SUMIFS(Pricing!$G:$G,Pricing!$A:$A,C22,Pricing!$B:$B,B22),"")) | L22: =IF(OR(I22="",J22=""),"",J22-I22) | M22: 0 | N22: 0 | O22: =IF(L22="","",L22-M22-N22) | P22: =IF(OR(O22="",I22=""),"",O22/I22) | Q22: =IF(OR(D22="",E22=""),"",MAX(1,ROUNDUP(E22-D22,0))) | R22: =IF(OR(P22="",Q22=""),"",(1+P22)^(365/Q22)-1)
A23: =IF(Sell_History!A23="","",Sell_History!A23) | B23: =IF(Sell_History!B23="","",Sell_History!B23) | C23: =IF(A23="","",IFERROR(INDEX(Buy_History!#REF!,MATCH(A23,Buy_History!$A:$A,0)),A23)) | D23: =IF(C23="","",IFERROR(INDEX(Buy_History!$C:$C,MATCH(C23,Buy_History!$A:$A,0)),"")) | E23: =IF(A23="","",IFERROR(SUMIFS(Sell_History!$D:$D,Sell_History!$A:$A,A23,Sell_History!$B:$B,B23),"")) | F23: =IF(A23="","",IF(SUMIFS(Sell_History!$E:$E,Sell_History!$A:$A,A23,Sell_History!$B:$B,B23)=0,"",SUMIFS(Sell_History!$E:$E,Sell_History!$A:$A,A23,Sell_History!$B:$B,B23))) | G23: =IF(C23="","",IFERROR(INDEX(Buy_History!$E:$E,MATCH(C23,Buy_History!$A:$A,0)),"")) | H23: =IF(C23="","",IFERROR(SUMIFS(Raw_Observations!$D:$D,Raw_Observations!$A:$A,C23,Raw_Observations!$B:$B,B23),"")) | I23: =IF(H23="","",IF(OR(F23="",G23="",G23=0),H23,H23*F23/G23)) | J23: =IFERROR(LOOKUP(2,1/((Order_History!$A$2:$A$200=A23)*(Order_History!$B$2:$B$200=B23)*(Order_History!$E$2:$E$200<=E23)),Order_History!$G$2:$G$200),"") -> 0 | K23: =IF(C23="","",IFERROR(SUMIFS(Pricing!$G:$G,Pricing!$A:$A,C23,Pricing!$B:$B,B23),"")) | L23: =IF(OR(I23="",J23=""),"",J23-I23) | M23: 0 | N23: 0 | O23: =IF(L23="","",L23-M23-N23) | P23: =IF(OR(O23="",I23=""),"",O23/I23) | Q23: =IF(OR(D23="",E23=""),"",MAX(1,ROUNDUP(E23-D23,0))) | R23: =IF(OR(P23="",Q23=""),"",(1+P23)^(365/Q23)-1)
A24: =IF(Sell_History!A24="","",Sell_History!A24) | B24: =IF(Sell_History!B24="","",Sell_History!B24) | C24: =IF(A24="","",IFERROR(INDEX(Buy_History!#REF!,MATCH(A24,Buy_History!$A:$A,0)),A24)) | D24: =IF(C24="","",IFERROR(INDEX(Buy_History!$C:$C,MATCH(C24,Buy_History!$A:$A,0)),"")) | E24: =IF(A24="","",IFERROR(SUMIFS(Sell_History!$D:$D,Sell_History!$A:$A,A24,Sell_History!$B:$B,B24),"")) | F24: =IF(A24="","",IF(SUMIFS(Sell_History!$E:$E,Sell_History!$A:$A,A24,Sell_History!$B:$B,B24)=0,"",SUMIFS(Sell_History!$E:$E,Sell_History!$A:$A,A24,Sell_History!$B:$B,B24))) | G24: =IF(C24="","",IFERROR(INDEX(Buy_History!$E:$E,MATCH(C24,Buy_History!$A:$A,0)),"")) | H24: =IF(C24="","",IFERROR(SUMIFS(Raw_Observations!$D:$D,Raw_Observations!$A:$A,C24,Raw_Observations!$B:$B,B24),"")) | I24: =IF(H24="","",IF(OR(F24="",G24="",G24=0),H24,H24*F24/G24)) | J24: =IFERROR(LOOKUP(2,1/((Order_History!$A$2:$A$200=A24)*(Order_History!$B$2:$B$200=B24)*(Order_History!$E$2:$E$200<=E24)),Order_History!$G$2:$G$200),"") -> 0 | K24: =IF(C24="","",IFERROR(SUMIFS(Pricing!$G:$G,Pricing!$A:$A,C24,Pricing!$B:$B,B24),"")) | L24: =IF(OR(I24="",J24=""),"",J24-I24) | M24: 0 | N24: 0 | O24: =IF(L24="","",L24-M24-N24) | P24: =IF(OR(O24="",I24=""),"",O24/I24) | Q24: =IF(OR(D24="",E24=""),"",MAX(1,ROUNDUP(E24-D24,0))) | R24: =IF(OR(P24="",Q24=""),"",(1+P24)^(365/Q24)-1)
A25: =IF(Sell_History!A25="","",Sell_History!A25) | B25: =IF(Sell_History!B25="","",Sell_History!B25) | C25: =IF(A25="","",IFERROR(INDEX(Buy_History!#REF!,MATCH(A25,Buy_History!$A:$A,0)),A25)) | D25: =IF(C25="","",IFERROR(INDEX(Buy_History!$C:$C,MATCH(C25,Buy_History!$A:$A,0)),"")) | E25: =IF(A25="","",IFERROR(SUMIFS(Sell_History!$D:$D,Sell_History!$A:$A,A25,Sell_History!$B:$B,B25),"")) | F25: =IF(A25="","",IF(SUMIFS(Sell_History!$E:$E,Sell_History!$A:$A,A25,Sell_History!$B:$B,B25)=0,"",SUMIFS(Sell_History!$E:$E,Sell_History!$A:$A,A25,Sell_History!$B:$B,B25))) | G25: =IF(C25="","",IFERROR(INDEX(Buy_History!$E:$E,MATCH(C25,Buy_History!$A:$A,0)),"")) | H25: =IF(C25="","",IFERROR(SUMIFS(Raw_Observations!$D:$D,Raw_Observations!$A:$A,C25,Raw_Observations!$B:$B,B25),"")) | I25: =IF(H25="","",IF(OR(F25="",G25="",G25=0),H25,H25*F25/G25)) | J25: =IFERROR(LOOKUP(2,1/((Order_History!$A$2:$A$200=A25)*(Order_History!$B$2:$B$200=B25)*(Order_History!$E$2:$E$200<=E25)),Order_History!$G$2:$G$200),"") -> 0 | K25: =IF(C25="","",IFERROR(SUMIFS(Pricing!$G:$G,Pricing!$A:$A,C25,Pricing!$B:$B,B25),"")) | L25: =IF(OR(I25="",J25=""),"",J25-I25) | M25: 0 | N25: 0 | O25: =IF(L25="","",L25-M25-N25) | P25: =IF(OR(O25="",I25=""),"",O25/I25) | Q25: =IF(OR(D25="",E25=""),"",MAX(1,ROUNDUP(E25-D25,0))) | R25: =IF(OR(P25="",Q25=""),"",(1+P25)^(365/Q25)-1)
A26: =IF(Sell_History!A26="","",Sell_History!A26) | B26: =IF(Sell_History!B26="","",Sell_History!B26) | C26: =IF(A26="","",IFERROR(INDEX(Buy_History!#REF!,MATCH(A26,Buy_History!$A:$A,0)),A26)) | D26: =IF(C26="","",IFERROR(INDEX(Buy_History!$C:$C,MATCH(C26,Buy_History!$A:$A,0)),"")) | E26: =IF(A26="","",IFERROR(SUMIFS(Sell_History!$D:$D,Sell_History!$A:$A,A26,Sell_History!$B:$B,B26),"")) | F26: =IF(A26="","",IF(SUMIFS(Sell_History!$E:$E,Sell_History!$A:$A,A26,Sell_History!$B:$B,B26)=0,"",SUMIFS(Sell_History!$E:$E,Sell_History!$A:$A,A26,Sell_History!$B:$B,B26))) | G26: =IF(C26="","",IFERROR(INDEX(Buy_History!$E:$E,MATCH(C26,Buy_History!$A:$A,0)),"")) | H26: =IF(C26="","",IFERROR(SUMIFS(Raw_Observations!$D:$D,Raw_Observations!$A:$A,C26,Raw_Observations!$B:$B,B26),"")) | I26: =IF(H26="","",IF(OR(F26="",G26="",G26=0),H26,H26*F26/G26)) | J26: =IFERROR(LOOKUP(2,1/((Order_History!$A$2:$A$200=A26)*(Order_History!$B$2:$B$200=B26)*(Order_History!$E$2:$E$200<=E26)),Order_History!$G$2:$G$200),"") -> 0 | K26: =IF(C26="","",IFERROR(SUMIFS(Pricing!$G:$G,Pricing!$A:$A,C26,Pricing!$B:$B,B26),"")) | L26: =IF(OR(I26="",J26=""),"",J26-I26) | M26: 0 | N26: 0 | O26: =IF(L26="","",L26-M26-N26) | P26: =IF(OR(O26="",I26=""),"",O26/I26) | Q26: =IF(OR(D26="",E26=""),"",MAX(1,ROUNDUP(E26-D26,0))) | R26: =IF(OR(P26="",Q26=""),"",(1+P26)^(365/Q26)-1)
A27: =IF(Sell_History!A27="","",Sell_History!A27) | B27: =IF(Sell_History!B27="","",Sell_History!B27) | C27: =IF(A27="","",IFERROR(INDEX(Buy_History!#REF!,MATCH(A27,Buy_History!$A:$A,0)),A27)) | D27: =IF(C27="","",IFERROR(INDEX(Buy_History!$C:$C,MATCH(C27,Buy_History!$A:$A,0)),"")) | E27: =IF(A27="","",IFERROR(SUMIFS(Sell_History!$D:$D,Sell_History!$A:$A,A27,Sell_History!$B:$B,B27),"")) | F27: =IF(A27="","",IF(SUMIFS(Sell_History!$E:$E,Sell_History!$A:$A,A27,Sell_History!$B:$B,B27)=0,"",SUMIFS(Sell_History!$E:$E,Sell_History!$A:$A,A27,Sell_History!$B:$B,B27))) | G27: =IF(C27="","",IFERROR(INDEX(Buy_History!$E:$E,MATCH(C27,Buy_History!$A:$A,0)),"")) | H27: =IF(C27="","",IFERROR(SUMIFS(Raw_Observations!$D:$D,Raw_Observations!$A:$A,C27,Raw_Observations!$B:$B,B27),"")) | I27: =IF(H27="","",IF(OR(F27="",G27="",G27=0),H27,H27*F27/G27)) | J27: =IFERROR(LOOKUP(2,1/((Order_History!$A$2:$A$200=A27)*(Order_History!$B$2:$B$200=B27)*(Order_History!$E$2:$E$200<=E27)),Order_History!$G$2:$G$200),"") -> 0 | K27: =IF(C27="","",IFERROR(SUMIFS(Pricing!$G:$G,Pricing!$A:$A,C27,Pricing!$B:$B,B27),"")) | L27: =IF(OR(I27="",J27=""),"",J27-I27) | M27: 0 | N27: 0 | O27: =IF(L27="","",L27-M27-N27) | P27: =IF(OR(O27="",I27=""),"",O27/I27) | Q27: =IF(OR(D27="",E27=""),"",MAX(1,ROUNDUP(E27-D27,0))) | R27: =IF(OR(P27="",Q27=""),"",(1+P27)^(365/Q27)-1)
A28: =IF(Sell_History!A28="","",Sell_History!A28) | B28: =IF(Sell_History!B28="","",Sell_History!B28) | C28: =IF(A28="","",IFERROR(INDEX(Buy_History!#REF!,MATCH(A28,Buy_History!$A:$A,0)),A28)) | D28: =IF(C28="","",IFERROR(INDEX(Buy_History!$C:$C,MATCH(C28,Buy_History!$A:$A,0)),"")) | E28: =IF(A28="","",IFERROR(SUMIFS(Sell_History!$D:$D,Sell_History!$A:$A,A28,Sell_History!$B:$B,B28),"")) | F28: =IF(A28="","",IF(SUMIFS(Sell_History!$E:$E,Sell_History!$A:$A,A28,Sell_History!$B:$B,B28)=0,"",SUMIFS(Sell_History!$E:$E,Sell_History!$A:$A,A28,Sell_History!$B:$B,B28))) | G28: =IF(C28="","",IFERROR(INDEX(Buy_History!$E:$E,MATCH(C28,Buy_History!$A:$A,0)),"")) | H28: =IF(C28="","",IFERROR(SUMIFS(Raw_Observations!$D:$D,Raw_Observations!$A:$A,C28,Raw_Observations!$B:$B,B28),"")) | I28: =IF(H28="","",IF(OR(F28="",G28="",G28=0),H28,H28*F28/G28)) | J28: =IFERROR(LOOKUP(2,1/((Order_History!$A$2:$A$200=A28)*(Order_History!$B$2:$B$200=B28)*(Order_History!$E$2:$E$200<=E28)),Order_History!$G$2:$G$200),"") -> 0 | K28: =IF(C28="","",IFERROR(SUMIFS(Pricing!$G:$G,Pricing!$A:$A,C28,Pricing!$B:$B,B28),"")) | L28: =IF(OR(I28="",J28=""),"",J28-I28) | M28: 0 | N28: 0 | O28: =IF(L28="","",L28-M28-N28) | P28: =IF(OR(O28="",I28=""),"",O28/I28) | Q28: =IF(OR(D28="",E28=""),"",MAX(1,ROUNDUP(E28-D28,0))) | R28: =IF(OR(P28="",Q28=""),"",(1+P28)^(365/Q28)-1)
A29: =IF(Sell_History!A29="","",Sell_History!A29) | B29: =IF(Sell_History!B29="","",Sell_History!B29) | C29: =IF(A29="","",IFERROR(INDEX(Buy_History!#REF!,MATCH(A29,Buy_History!$A:$A,0)),A29)) | D29: =IF(C29="","",IFERROR(INDEX(Buy_History!$C:$C,MATCH(C29,Buy_History!$A:$A,0)),"")) | E29: =IF(A29="","",IFERROR(SUMIFS(Sell_History!$D:$D,Sell_History!$A:$A,A29,Sell_History!$B:$B,B29),"")) | F29: =IF(A29="","",IF(SUMIFS(Sell_History!$E:$E,Sell_History!$A:$A,A29,Sell_History!$B:$B,B29)=0,"",SUMIFS(Sell_History!$E:$E,Sell_History!$A:$A,A29,Sell_History!$B:$B,B29))) | G29: =IF(C29="","",IFERROR(INDEX(Buy_History!$E:$E,MATCH(C29,Buy_History!$A:$A,0)),"")) | H29: =IF(C29="","",IFERROR(SUMIFS(Raw_Observations!$D:$D,Raw_Observations!$A:$A,C29,Raw_Observations!$B:$B,B29),"")) | I29: =IF(H29="","",IF(OR(F29="",G29="",G29=0),H29,H29*F29/G29)) | J29: =IFERROR(LOOKUP(2,1/((Order_History!$A$2:$A$200=A29)*(Order_History!$B$2:$B$200=B29)*(Order_History!$E$2:$E$200<=E29)),Order_History!$G$2:$G$200),"") -> 0 | K29: =IF(C29="","",IFERROR(SUMIFS(Pricing!$G:$G,Pricing!$A:$A,C29,Pricing!$B:$B,B29),"")) | L29: =IF(OR(I29="",J29=""),"",J29-I29) | M29: 0 | N29: 0 | O29: =IF(L29="","",L29-M29-N29) | P29: =IF(OR(O29="",I29=""),"",O29/I29) | Q29: =IF(OR(D29="",E29=""),"",MAX(1,ROUNDUP(E29-D29,0))) | R29: =IF(OR(P29="",Q29=""),"",(1+P29)^(365/Q29)-1)
... A200: =IF(Sell_History!A200="","",Sell_History!A200) | B200: =IF(Sell_History!B200="","",Sell_History!B200) | C200: =IF(A200="","",IFERROR(INDEX(Buy_History!#REF!,MATCH(A200,Buy_History!$A:$A,0)),A200)) | D200: =IF(C200="","",IFERROR(INDEX(Buy_History!$C:$C,MATCH(C200,Buy_History!$A:$A,0)),"")) | E200: =IF(A200="","",IFERROR(SUMIFS(Sell_History!$D:$D,Sell_History!$A:$A,A200,Sell_History!$B:$B,B200),"")) | F200: =IF(A200="","",IF(SUMIFS(Sell_History!$E:$E,Sell_History!$A:$A,A200,Sell_History!$B:$B,B200)=0,"",SUMIFS(Sell_History!$E:$E,Sell_History!$A:$A,A200,Sell_History!$B:$B,B200))) | G200: =IF(C200="","",IFERROR(INDEX(Buy_History!$E:$E,MATCH(C200,Buy_History!$A:$A,0)),"")) | H200: =IF(C200="","",IFERROR(SUMIFS(Raw_Observations!$D:$D,Raw_Observations!$A:$A,C200,Raw_Observations!$B:$B,B200),"")) | I200: =IF(H200="","",IF(OR(F200="",G200="",G200=0),H200,H200*F200/G200)) | J200: =IFERROR(LOOKUP(2,1/((Order_History!$A$2:$A$200=A200)*(Order_History!$B$2:$B$200=B200)*(Order_History!$E$2:$E$200<=E200)),Order_History!$G$2:$G$200),"") -> 0 | K200: =IF(C200="","",IFERROR(SUMIFS(Pricing!$G:$G,Pricing!$A:$A,C200,Pricing!$B:$B,B200),"")) | L200: =IF(OR(I200="",J200=""),"",J200-I200) | M200: 0 | N200: 0 | O200: =IF(L200="","",L200-M200-N200) | P200: =IF(OR(O200="",I200=""),"",O200/I200) | Q200: =IF(OR(D200="",E200=""),"",MAX(1,ROUNDUP(E200-D200,0))) | R200: =IF(OR(P200="",Q200=""),"",(1+P200)^(365/Q200)-1)
